{"code":0,"message":"0","ttl":1,"data":{"list":{"tlist":{"1":{"tid":1,"count":6,"name":"动画"},"119":{"tid":119,"count":2,"name":"鬼畜"},"129":{"tid":129,"count":3,"name":"舞蹈"},"155":{"tid":155,"count":6,"name":"时尚"},"160":{"tid":160,"count":3459,"name":"生活"},"165":{"tid":165,"count":5,"name":"广告"},"177":{"tid":177,"count":8,"name":"纪录片"},"181":{"tid":181,"count":69,"name":"影视"},"188":{"tid":188,"count":14,"name":"数码"},"3":{"tid":3,"count":19,"name":"音乐"},"36":{"tid":36,"count":2556,"name":"科技"},"4":{"tid":4,"count":9,"name":"游戏"},"5":{"tid":5,"count":52,"name":"娱乐"}},"vlist":[{"comment":388,"typeid":75,"play":324363,"pic":"//i2.hdslb.com/bfs/archive/281b9102b44ccd0f0ae977e51824418f7986740d.jpg","subtitle":"","description":"不是毛熊，对不起，让大家失望了！","copyright":"","title":"诶诶诶正直播新闻呢，好像混进了什么奇怪的东西？","review":0,"author":"观察者网","mid":10330740,"created":1495352864,"length":"00:57","video_review":348,"aid":10722941,"bvid":"BV1Qx411v7zv","hide_click":false,"is_pay":0,"is_union_video":0},{"comment":2033,"typeid":21,"play":280922,"pic":"//i1.hdslb.com/bfs/archive/ccba653e14f18ebb8589db31bdf968d4dfc61671.png","subtitle":"","description":"5月18日，台湾高雄市发生惊悚凶杀案。一对兄妹因是否外出问题发生争吵，哥哥拿刀当街将妹妹的头砍下，头颅滚到人行道上，吓坏路人。而随后网友的关注点被台湾的记者给转移了，当记者去采访兄妹家属时，记者态度傲慢，引起网友批判...","copyright":"","title":"台湾发生惊悚砍头案 而记者是这样采访的...","review":0,"author":"观察者网","mid":10330740,"created":1495158205,"length":"02:05","video_review":1512,"aid":10659058,"bvid":"BV1Yx411v7Ui","hide_click":false,"is_pay":0,"is_union_video":0},{"comment":309,"typeid":21,"play":44993,"pic":"//i2.hdslb.com/bfs/archive/d3c08d4f1494f07409b0a859c5913df52af57aad.jpg","subtitle":"","description":"面对美国媒体的又一轮狂轰滥炸，特朗普这回进入委屈模式，说自己是史上最受欺负总统，但你们还记得他当年生怼媒体的雄姿吗？这是今年2月特朗普在演讲中轰假新闻的片段，虽然语句朴实，但还真有几分道理","copyright":"","title":"还记得大明湖畔，特朗普怒斥媒体的雄姿吗？","review":0,"author":"观察者网","mid":10330740,"created":1495098876,"length":"02:13","video_review":185,"aid":10645950,"bvid":"BV1Jx411v7UX","hide_click":false,"is_pay":0,"is_union_video":0},{"comment":486,"typeid":21,"play":147266,"pic":"//i1.hdslb.com/bfs/archive/ad8da8ddae430aad24d748dadefd551548a024b7.jpg","subtitle":"","description":"【来，干了这碗唐氏浓鸡汤】通俄，泄密，妨碍司法公正…这两天特朗普又遭到美国媒体口诛笔伐，昨天他在美国海岸警卫队学院演讲时直言历史上没有一个政治家遭受过如此不公的待遇，但尽管前方荆棘遍布，他仍会抗争到底。","copyright":"","title":"啊没有一点点防备…就被这位70来岁的老人灌了一碗浓鸡汤","review":0,"author":"观察者网","mid":10330740,"created":1495089301,"length":"01:44","video_review":726,"aid":10642554,"bvid":"BV1Ex411v75V","hide_click":false,"is_pay":0,"is_union_video":0},{"comment":1247,"typeid":21,"play":68753,"pic":"//i2.hdslb.com/bfs/archive/07bb9bca849471e88f3434f98cbd8b07acdc2ce5.jpg","subtitle":"","description":"近日，一段“孩童在游泳馆溺水挣扎72秒”的视频让不少网友看得心碎。5月16日，山东某儿童游泳馆内，一名孩童正在泳池游泳，突然因为身体前倾，失去平衡，头朝下倒立溺水。期间孩子家属、游泳馆工作人员均未发现，孩童在水中挣扎了72秒后才被救出。目前孩子已脱离危险，要是再晚些被救，后果不堪设想。","copyright":"","title":"孩童在游泳馆倒立溺水挣扎72秒 身旁无人看护","review":0,"author":"观察者网","mid":10330740,"created":1495085986,"length":"01:54","video_review":324,"aid":10641638,"bvid":"BV1Ex411v7hu","hide_click":false,"is_pay":0,"is_union_video":0},{"comment":628,"typeid":21,"play":61196,"pic":"//i1.hdslb.com/bfs/archive/5f9da760bc3c32b27b016aab15c9f8cb62f8d41f.jpg","subtitle":"","description":"自己选的试验，喊着也要……啊啊啊啊啊啊啊啊啊为什么会想试这个啊Fxxk！","copyright":"","title":"美高中生体验被喷辣椒水，那惨叫声……","review":0,"author":"观察者网","mid":10330740,"created":1495081257,"length":"01:37","video_review":323,"aid":10640040,"bvid":"BV1jx411v7Df","hide_click":false,"is_pay":0,"is_union_video":0},{"comment":285,"typeid":21,"play":51027,"pic":"//i2.hdslb.com/bfs/archive/213299bb693f4986a598110dc10648573e9d23d5.jpg","subtitle":"","description":"昨天普京和意大利总理召开联合新闻发布会，有记者问到 俄罗斯“被泄密”的问题，普京表示如果美方同意，俄罗斯乐意公开会谈记录；他还斥责美国政坛窝里斗的人不是真蠢就是卑鄙；至于给特朗普打几分，普京的回答真是克制又有深意…","copyright":"","title":"普京的日常耿直系列……回应“被泄密”篇","review":0,"author":"观察者网","mid":10330740,"created":1495079118,"length":"02:35","video_review":296,"aid":10638885,"bvid":"BV17x411v7Gw","hide_click":false,"is_pay":0,"is_union_video":0},{"comment":847,"typeid":124,"play":86011,"pic":"//i2.hdslb.com/bfs/archive/81e670e9fff8888cd1d04981f18f4b9e73ea073e.jpg","subtitle":"","description":"中国模式是一届接着一届改，西方模式是一届对着一届干。去一些国家介绍中国模式，交流的外国人感触：邓小平决定建立开发区，就建在深圳，在我们国家肯定要建在总统家乡。","copyright":"","title":"张维为：中国搞战略对接，对“第四种国家”要谨慎","review":0,"author":"观察者网","mid":10330740,"created":1495016983,"length":"06:50","video_review":649,"aid":10626680,"bvid":"BV1Wx411v7Le","hide_click":false,"is_pay":0,"is_union_video":0},{"comment":531,"typeid":39,"play":64475,"pic":"//i2.hdslb.com/bfs/archive/44ba34e94e3e1f6b3a7801ec0adf7c8e24d0849a.jpg","subtitle":"","description":"陈平教授不仅仅是一位经济学家，也是位物理学博士，师从诺贝尔化学奖获得者普里戈金。陈平教授把文理科相结合，首先发现经济混沌的经验证据。具体研究的东西小编也有点捉急，总之非常厉害，是一位奇人。","copyright":"","title":"【思想者论坛】不要神话经济生活中那只“看不见的手”","review":0,"author":"观察者网","mid":10330740,"created":1495016813,"length":"19:29","video_review":1002,"aid":10626067,"bvid":"BV1Wx411v7Tp","hide_click":false,"is_pay":0,"is_union_video":0},{"comment":909,"typeid":21,"play":45455,"pic":"//i1.hdslb.com/bfs/archive/7cefda95d650653fbdd3a74a2a545e20d54ff146.jpg","subtitle":"","description":"还记得那位拄着拐杖参加一带一路峰会的捷克总统泽曼吗？昨天他专程来到南京，携妻子参观南京大屠杀遇难同胞纪念馆，并敬献花圈。泽曼今年73岁，是首位参观该馆的在职外国总统。网友：捷克有什么好吃的？我们买！","copyright":"","title":"话说捷克有什么好吃的？我们买！","review":0,"author":"观察者网","mid":10330740,"created":1495003196,"length":"01:08","video_review":279,"aid":10621234,"bvid":"BV1px411v77W","hide_click":false,"is_pay":0,"is_union_video":0},{"comment":331,"typeid":21,"play":46707,"pic":"//i0.hdslb.com/bfs/archive/6b8435066cf00ef2fbd3c38b766d648893441a4e.jpg","subtitle":"","description":"台湾大学生地铁快闪走秀，车厢变T台！","copyright":"","title":"台湾大学生地铁快闪走秀，车厢变T台！","review":0,"author":"观察者网","mid":10330740,"created":1495003083,"length":"01:09","video_review":184,"aid":10621089,"bvid":"BV1px411v73P","hide_click":false,"is_pay":0,"is_union_video":0},{"comment":256,"typeid":21,"play":13322,"pic":"//i0.hdslb.com/bfs/archive/dc420d8ca5a5f6165526036eb4267e8e8aad8cf5.jpg","subtitle":"","description":"心疼宝宝一万点！5月14日，日本神奈川县举行了一年一度的“婴儿啼哭大赛”。相扑手抱着婴儿，想尽办法使婴儿哭泣。比赛规则十分简单，先哭的婴儿或是哭的时间长的婴儿获胜。这项比赛有着400年历史传统，很多父母相信这能够给孩子带来健康。","copyright":"","title":"宝宝心理苦 但宝宝还不得不哭","review":0,"author":"观察者网","mid":10330740,"created":1494927097,"length":"01:25","video_review":101,"aid":10603506,"bvid":"BV1Nx411v7oa","hide_click":false,"is_pay":0,"is_union_video":0},{"comment":346,"typeid":21,"play":103566,"pic":"//i0.hdslb.com/bfs/archive/79343227dd7cad4e03b9d9054264d2b639405c5e.jpg","subtitle":"","description":"昨天傍晚普京在北京举行针对俄罗斯媒体的记者招待会，会上回应了弹钢琴的事儿，而被问到和特朗普见面前要弹啥时，普京思考片刻，然后这样回答……","copyright":"","title":"等习大大时弹了《莫斯科之窗》，等特朗普时要弹啥？","review":0,"author":"观察者网","mid":10330740,"created":1494926866,"length":"02:04","video_review":377,"aid":10603585,"bvid":"BV1Nx411v74v","hide_click":false,"is_pay":0,"is_union_video":0},{"comment":571,"typeid":96,"play":32873,"pic":"//i1.hdslb.com/bfs/archive/860e4efe50338a8c92f464cb404deb341f87ae4f.jpg","subtitle":"","description":"日前，观察者网和复旦大学中国研究院共同举办了“思想者论坛”，国内外众多学者大咖齐聚上海，以“裂变与重构”为主题，探讨中国道路与中国话语问题。香港中文大学王绍光教授讲解了西方“自由民主”所遇到的困局与危机。","copyright":"","title":"【思想者论坛】选代表和选领导人是一码事吗？","review":0,"author":"观察者网","mid":10330740,"created":1494908581,"length":"11:03","video_review":513,"aid":10598015,"bvid":"BV15x411v7y5","hide_click":false,"is_pay":0,"is_union_video":0},{"comment":382,"typeid":96,"play":41564,"pic":"//i1.hdslb.com/bfs/archive/15b54bc6d591d4f70ea8c6d26f77bbed9de07642.jpg","subtitle":"","description":"http://www.bilibili.com/video/av10565415/\n这是我们好基友观视频工作室最新推出的作品，希望大家多多关注哟~~~http://www.bilibili.com/video/av10565415/","copyright":"","title":"张维为谈一带一路：千年未有之大变局！","review":0,"author":"观察者网","mid":10330740,"created":1494908515,"length":"19:40","video_review":483,"aid":10597832,"bvid":"BV15x411v7qJ","hide_click":false,"is_pay":0,"is_union_video":0},{"comment":166,"typeid":163,"play":49833,"pic":"//i0.hdslb.com/bfs/archive/d554af00f3b313cf9935e4efdcee585c48ad4e35.jpg","subtitle":"","description":"女排世俱杯落幕，朱婷获得本届比赛MVP与最佳主攻，入选最佳阵容。“核武器！信得过单位！霸气！势不可挡”，3分钟看朱婷世俱杯决赛精彩表现！","copyright":"","title":"朱婷狂赚MVP荣光加身！央视解说花式赞不停↖(^ω^)↗","review":0,"author":"观察者网","mid":10330740,"created":1494901665,"length":"02:57","video_review":221,"aid":10596234,"bvid":"BV1Gx411v7Z7","hide_click":false,"is_pay":0,"is_union_video":0},{"comment":1198,"typeid":21,"play":129488,"pic":"//i2.hdslb.com/bfs/archive/30b2b693d99eec857d796219217eca6522349805.jpg","subtitle":"","description":"西方媒体总是喜欢渲染中国工人到海外抢当地人饭碗，英国商会中国区主席则表示，中国工人到国外和英国殖民时期不一样，他们不是去统治的，而是真正地去帮他们解决问题。","copyright":"","title":"中国工人在海外抢饭碗？这位英国人第一个不答应！","review":0,"author":"观察者网","mid":10330740,"created":1494842208,"length":"02:19","video_review":272,"aid":10582494,"bvid":"BV1fx411e7rf","hide_click":false,"is_pay":0,"is_union_video":0},{"comment":429,"typeid":21,"play":125345,"pic":"//i0.hdslb.com/bfs/archive/12da302d03ff9b49b46d503939a7b0aad3a5aa76.jpg","subtitle":"","description":"昨天“一带一路”峰会开幕，俄罗斯和捷克高层会面，两国大佬开起玩笑，但万万没想到，这回“耿直”的是捷克总统。。。","copyright":"","title":"捷克总统和普京他们开玩笑，这回耿直的竟不是俄罗斯人。。。","review":0,"author":"观察者网","mid":10330740,"created":1494827357,"length":"00:18","video_review":36,"aid":10577438,"bvid":"BV1Zx411e7Ry","hide_click":false,"is_pay":0,"is_union_video":0},{"comment":603,"typeid":21,"play":34892,"pic":"//i2.hdslb.com/bfs/archive/ad1b4bcec4441c7ff98e7fd42d7b37b279b5ee5f.png","subtitle":"","description":"中欧班列，是指往来于中国与欧洲以及“一带一路”沿线国家的集装箱国际铁路联运班列。截至目前，中国铁路已经铺画了中欧班列运行线51条，到达欧洲。戳视频看看这些中欧班列究竟是怎么开的呢！","copyright":"","title":"一带一路上的中欧班列，究竟怎么开？","review":0,"author":"观察者网","mid":10330740,"created":1494729413,"length":"03:41","video_review":175,"aid":10547848,"bvid":"BV1Sx411e76N","hide_click":false,"is_pay":0,"is_union_video":0},{"comment":450,"typeid":138,"play":275468,"pic":"//i0.hdslb.com/bfs/archive/dd630b2915e43728a2f5b3b07f2a2681d85a01f8.jpg","subtitle":"","description":"这位11岁的小王子斯维尔-马格努斯(Prince Sverre Magnus)，是哈康王子的孩子，也是第三顺位挪威王位的继承人。","copyright":"","title":"当大家一本正经为国王王后祝寿时，挪威小王子在放飞自我的路上越走越远…","review":0,"author":"观察者网","mid":10330740,"created":1494563030,"length":"00:52","video_review":242,"aid":10494707,"bvid":"BV1Cx411e7e5","hide_click":false,"is_pay":0,"is_union_video":0},{"comment":735,"typeid":21,"play":61270,"pic":"//i0.hdslb.com/bfs/archive/02584b0e9d1b9c9fbd947b50743c13c6ed904b56.png","subtitle":"","description":"近日，印度一名19岁少女卡敦被当地土地开发商扔进土坑中活埋，只因为她的父亲拒绝对方买地的要求。所幸少女命大，被家人及时发现而获救。","copyright":"","title":"开发商雇凶将少女活埋 只因其父亲拒绝卖地","review":0,"author":"观察者网","mid":10330740,"created":1494562256,"length":"01:04","video_review":171,"aid":10494589,"bvid":"BV1Cx411e7is","hide_click":false,"is_pay":0,"is_union_video":0},{"comment":129,"typeid":75,"play":35681,"pic":"//i2.hdslb.com/bfs/archive/3cfcfe510640c15fa0d5c7f2dc7aa0cece18fef7.jpg","subtitle":"","description":"今日份儿的观察小动物~请各位老爷查收~","copyright":"","title":"哈哈你们平常不傲娇着吗~怎么见到个扫地机器人就怂了~","review":0,"author":"观察者网","mid":10330740,"created":1494495923,"length":"00:21","video_review":39,"aid":10479187,"bvid":"BV19x411m7ow","hide_click":false,"is_pay":0,"is_union_video":0},{"comment":2379,"typeid":21,"play":391288,"pic":"//i1.hdslb.com/bfs/archive/74a42ea2e45aea2f302916545035f65e792d56ce.jpg","subtitle":"","description":"眼红不？继续眼红吧嘻嘻","copyright":"","title":"一带一路峰会要开啦 这可把美国智库急死了","review":0,"author":"观察者网","mid":10330740,"created":1494492561,"length":"03:32","video_review":743,"aid":10477968,"bvid":"BV1Rx411m7uV","hide_click":false,"is_pay":0,"is_union_video":0},{"comment":245,"typeid":138,"play":30276,"pic":"//i2.hdslb.com/bfs/archive/6fef83ede8629f06c9453a9132612791b5840500.jpg","subtitle":"","description":"都是真实画面，没有六毛钱特效","copyright":"","title":"在太极表演上，海峡两岸还真是一家亲","review":0,"author":"观察者网","mid":10330740,"created":1494484626,"length":"01:37","video_review":234,"aid":10474934,"bvid":"BV1Xx411m7Ba","hide_click":false,"is_pay":0,"is_union_video":0},{"comment":208,"typeid":21,"play":26790,"pic":"//i2.hdslb.com/bfs/archive/fd53a3cf780635cccbe7df0e2a826031fcf32281.jpg","subtitle":"","description":"拉夫罗夫：ㄟ( ▔, ▔ )ㄏ\n普大帝： (´・ω・`)","copyright":"","title":"FBI局长科米被炒，俄罗斯说：  (´・ω・`)","review":0,"author":"观察者网","mid":10330740,"created":1494483590,"length":"01:23","video_review":113,"aid":10474145,"bvid":"BV19x411m7cS","hide_click":false,"is_pay":0,"is_union_video":0},{"comment":213,"typeid":21,"play":83302,"pic":"//i1.hdslb.com/bfs/archive/e2f6ae8722b9b8edc546f62b61225e2866f4a2d3.jpg","subtitle":"","description":"刚炒掉FBI局长科米，特朗普就会见了俄罗斯外长和尼克松国务卿基辛格，这下美国记者可坐不住了……","copyright":"","title":"什么味儿？历史重演的气味吗？！","review":0,"author":"观察者网","mid":10330740,"created":1494477202,"length":"01:09","video_review":143,"aid":10472014,"bvid":"BV1Qx411m7GH","hide_click":false,"is_pay":0,"is_union_video":0},{"comment":510,"typeid":21,"play":43007,"pic":"//i0.hdslb.com/bfs/archive/4966626e57222275ae6d70ae2db105c641ef5112.png","subtitle":"","description":"5月8日晚，美国佛罗里达州劳德代尔堡-好莱坞国际机场因为航班被取消，愤怒的乘客和工作人员、警方爆发冲突，现场一片混乱，有多名乘客因此被捕。","copyright":"","title":"美国机场航班遭取消 乘客骚乱与警方爆发冲突","review":0,"author":"观察者网","mid":10330740,"created":1494476405,"length":"00:51","video_review":199,"aid":10471581,"bvid":"BV1Qx411m7wg","hide_click":false,"is_pay":0,"is_union_video":0},{"comment":271,"typeid":21,"play":30377,"pic":"//i0.hdslb.com/bfs/archive/db65106b5381ff43e2f239fbdfad2e7dbe1c9b03.jpg","subtitle":"","description":"这蜜汁少女心……","copyright":"","title":"台湾大叔沉迷娃娃机无法自拔，去警局骗钱继续抓…","review":0,"author":"观察者网","mid":10330740,"created":1494412303,"length":"00:47","video_review":45,"aid":10458641,"bvid":"BV1Zx411m7qw","hide_click":false,"is_pay":0,"is_union_video":0},{"comment":184,"typeid":75,"play":44051,"pic":"//i0.hdslb.com/bfs/archive/69dc0d6f1dee6a29b8f2fd60d631a2a013157feb.jpg","subtitle":"","description":"我可能看到一群神经喵，无敌爆炸可爱到萌死啦～～","copyright":"","title":"没想到你是这样的喵","review":0,"author":"观察者网","mid":10330740,"created":1494407402,"length":"02:45","video_review":214,"aid":10456708,"bvid":"BV1dx411m71L","hide_click":false,"is_pay":0,"is_union_video":0},{"comment":583,"typeid":21,"play":42999,"pic":"//i2.hdslb.com/bfs/archive/805e700ecbfa5f40ee386fcc9aec15325f92ca46.jpg","subtitle":"","description":"日本人有多怕朝鲜导弹？广告都在教你怎么避难。该教学视频一周内获得460万播放量，同时作为富士电视台《志村笑》节目片尾全日本播放……","copyright":"","title":"朝鲜月月射导弹，日本人吓得都开始唱歌了","review":0,"author":"观察者网","mid":10330740,"created":1494402714,"length":"03:11","video_review":456,"aid":10454966,"bvid":"BV1ox411m74V","hide_click":false,"is_pay":0,"is_union_video":0}]},"page":{"count":6208,"pn":183,"ps":30}}}