{"code":0,"message":"0","ttl":1,"data":{"list":{"tlist":{"1":{"tid":1,"count":6,"name":"动画"},"119":{"tid":119,"count":2,"name":"鬼畜"},"129":{"tid":129,"count":3,"name":"舞蹈"},"155":{"tid":155,"count":6,"name":"时尚"},"160":{"tid":160,"count":3459,"name":"生活"},"165":{"tid":165,"count":5,"name":"广告"},"177":{"tid":177,"count":8,"name":"纪录片"},"181":{"tid":181,"count":69,"name":"影视"},"188":{"tid":188,"count":14,"name":"数码"},"3":{"tid":3,"count":19,"name":"音乐"},"36":{"tid":36,"count":2556,"name":"科技"},"4":{"tid":4,"count":9,"name":"游戏"},"5":{"tid":5,"count":52,"name":"娱乐"}},"vlist":[{"comment":628,"typeid":21,"play":74536,"pic":"//i1.hdslb.com/bfs/archive/4ba9b332bd7a43fccd647a0f114b2537c6e3f780.jpg","subtitle":"","description":"【巴西大坝坍塌引发泥石流 已造成50人死200人失踪】1月25日，巴西米纳斯吉拉斯州布鲁马迪纽市的一座大坝发生爆裂并引发泥石流，事故已造成至少50人死亡200多人失踪。据报道，大坝为巴西淡水河谷公司所有，该公司是世界第一大铁矿石生产和出口商。2015年，此公司的另一座大坝也曾发生过类似坍塌事故并造成19人死亡。","copyright":"","title":"巴西大坝坍塌引发泥石流 已造成50人死200人失踪","review":0,"author":"观察者网","mid":10330740,"created":1548476746,"length":"00:48","video_review":122,"aid":41733265,"bvid":"BV1et41147Zd","hide_click":false,"is_pay":0,"is_union_video":0},{"comment":1070,"typeid":96,"play":358630,"pic":"//i2.hdslb.com/bfs/archive/3e24107652e2a72c2929a62a1e519808e17794da.jpg","subtitle":"","description":"世界银行行长金墉宣布将于2月1日辞职，许多媒体和高层都批评美国垄断世界银行行长的行为，呼吁推举非美国公民出任行长。其实美国在二战以后通过制度设计控制了世界金融体系，而世界银行和国际货币基金组织就是在前台执行美国利益的白手套。本期《骁话一下》，我们就来聊聊美国在国际金融机构中的霸权行为。","copyright":"","title":"骁话一下：美国在国际金融机构中的霸权行为","review":0,"author":"观察者网","mid":10330740,"created":1548468605,"length":"08:58","video_review":1975,"aid":41672028,"bvid":"BV1ot411b7za","hide_click":false,"is_pay":0,"is_union_video":0},{"comment":1449,"typeid":21,"play":185548,"pic":"//i2.hdslb.com/bfs/archive/dddafbef8a0439fb7df4f68eedffb24c1989ec98.jpg","subtitle":"","description":"【特朗普宣布重启政府三周 若建墙谈判仍失败将宣布紧急状态】1月25日，特朗普在白宫宣布重启政府三周至2月15日，期间两党会就边境墙问题进行谈判。若三周后谈判仍旧难达共识，那么届时不是政府重新关门，就是他宣布紧急状态。","copyright":"","title":"特朗普宣布重启政府三周 若建墙谈判仍失败将宣布紧急状态","review":0,"author":"观察者网","mid":10330740,"created":1548468313,"length":"01:55","video_review":586,"aid":41721646,"bvid":"BV1rt41147nV","hide_click":false,"is_pay":0,"is_union_video":0},{"comment":919,"typeid":21,"play":102474,"pic":"//i1.hdslb.com/bfs/archive/a2e29590bb942e9707a3c548fd248726e6248bf9.jpg","subtitle":"","description":"日本网球名将大阪直美日前成为了日清泡面广告主角，并以漫画人物形态出现，不料却引发一场风波——作为海地与日本的混血儿，肤色的黝黑的大阪直美被“漂白”了。事件发酵引起争议后，日清食品应大阪直美经济公司的要求，在23日撤下广告。次日，大阪直美在采访时作出回应：","copyright":"","title":"大阪直美“被漂白” 日清撤泡面广告致歉","review":0,"author":"观察者网","mid":10330740,"created":1548417512,"length":"01:05","video_review":196,"aid":41672902,"bvid":"BV1ft411b76X","hide_click":false,"is_pay":0,"is_union_video":0},{"comment":705,"typeid":21,"play":58208,"pic":"//i2.hdslb.com/bfs/archive/2e12e635b504b0e0f29206023ca4fd2a3541bc55.jpg","subtitle":"","description":"最近编辑部奶茶车越发越频，本期编辑部的日常灵魂质问：现在年轻人为啥就这么爱喝奶茶？","copyright":"","title":"编辑部问答：为什么越来越多人沉迷奶茶无法自拔？","review":0,"author":"观察者网","mid":10330740,"created":1548405415,"length":"03:34","video_review":473,"aid":41659409,"bvid":"BV1At41187rp","hide_click":false,"is_pay":0,"is_union_video":0},{"comment":6509,"typeid":21,"play":1485245,"pic":"//i1.hdslb.com/bfs/archive/857204697ec83ae5493c67f68dd6803254b5c39a.jpg","subtitle":"","description":"【还在为建墙吵架 美民主党议员：人家中国都登到月球背面了！】当地时间1月24日，美国民主党籍参议员迈克尔·贝内特忽然在国会暴怒，大声斥责特朗普因建墙导致政府关门。他激动地说：“我们政府关门的时候，人家中国的宇宙飞船都登到月球背面了！”","copyright":"","title":"还在为建墙吵架 美民主党议员：人家中国都登到月球背面了！","review":0,"author":"观察者网","mid":10330740,"created":1548402446,"length":"01:35","video_review":4383,"aid":41652130,"bvid":"BV1ct411874f","hide_click":false,"is_pay":0,"is_union_video":0},{"comment":1546,"typeid":201,"play":104763,"pic":"//i2.hdslb.com/bfs/archive/a41a1ae04e66d5e67179255b9afca9d2f5702e1b.jpg","subtitle":"","description":"2016年3月DeepMind团队的AlphaGo击败了世界围棋顶级棋手李世石，但在AlphaGo还名不见经传时，它先是与职业棋手樊麾较量取得胜利，接着该团队设计的新的AlphaStar同样击败了两名《星际争霸2》的职业选手TLO和MaNa。","copyright":"","title":"《星际2》 人类首战告负","review":0,"author":"观察者网","mid":10330740,"created":1548398072,"length":"01:11","video_review":228,"aid":41649704,"bvid":"BV1wt41187cf","hide_click":false,"is_pay":0,"is_union_video":0},{"comment":2057,"typeid":21,"play":114064,"pic":"//i0.hdslb.com/bfs/archive/416fa3bf8cb1bd1f7a240aa3e4b7490d049114a8.jpg","subtitle":"","description":"【联邦雇员去收容所领餐 美商务部长：何不去贷款！】1月24日，美国商务部长罗斯在接受记者提问时，提及80万联邦雇员因为政府关门拿不到工资而不得不去收容所领餐食的事情，他竟然回答说：“我实在搞不懂他们为什么不去贷款，不就是要付点利息钱嘛！”","copyright":"","title":"联邦雇员去收容所领餐 美商务部长：何不去贷款！","review":0,"author":"观察者网","mid":10330740,"created":1548392531,"length":"02:27","video_review":455,"aid":41633751,"bvid":"BV12t411b7sZ","hide_click":false,"is_pay":0,"is_union_video":0},{"comment":1124,"typeid":21,"play":169045,"pic":"//i0.hdslb.com/bfs/archive/b720952fa0b3a5b03caef029e4b471918a41d3fb.jpg","subtitle":"","description":"1月24日，在国务院新闻办公室的举行的有关“长城保护”的新闻发布会上，来自美国《华盛顿邮报》的记者向国家文物局局长刘玉珠提出了一个问题，“您对特朗普总统的边境墙有什么看法？您觉得特朗普总统可以从中国长城这学到什么？” 刘玉珠局长笑着回应道：“这和长城保护完全是两个概念。”","copyright":"","title":"在关于“长城保护”的发布会上 美国记者问了个关于特朗普的问题","review":0,"author":"观察者网","mid":10330740,"created":1548325101,"length":"01:36","video_review":434,"aid":41578844,"bvid":"BV18t411b72D","hide_click":false,"is_pay":0,"is_union_video":0},{"comment":826,"typeid":21,"play":199373,"pic":"//i2.hdslb.com/bfs/archive/7b7bc25917108136dbf4e2569ab0955a6060fe79.jpg","subtitle":"","description":"墨西哥。女儿冲出家门后，妈妈赶紧跟上，并顺手扔了一只拖鞋……","copyright":"","title":"妈，你啥时候练的？！╥﹏╥","review":0,"author":"观察者网","mid":10330740,"created":1548318191,"length":"00:18","video_review":175,"aid":41568269,"bvid":"BV1xt411b7tq","hide_click":false,"is_pay":0,"is_union_video":0},{"comment":1679,"typeid":21,"play":237829,"pic":"//i2.hdslb.com/bfs/archive/284040ac6a3394949a5b2ea8d860298938404042.jpg","subtitle":"","description":"【非法移民：你家有墙我有长梯！】长梯长梯，偷渡不愁，你家有墻，我有长梯。23日，美国亚利桑那州边防局发布了一段非法移民翻越边境墙的视频。视频中，118名主要来自危地马拉的非法移民在长梯的帮助下顺利地翻越了高约5.5米的边境高墙，然而翻墙的过程被监控摄像头全部记录下来，边防警察很快出动将非法越境移民全部逮捕。","copyright":"","title":"非法移民：你家有墙我有长梯！","review":0,"author":"观察者网","mid":10330740,"created":1548314528,"length":"00:38","video_review":233,"aid":41562482,"bvid":"BV1vt411b7zR","hide_click":false,"is_pay":0,"is_union_video":0},{"comment":644,"typeid":21,"play":135973,"pic":"//i1.hdslb.com/bfs/archive/0294e9b62a950dbce5140eb600433f7a37090f15.jpg","subtitle":"","description":"【国情咨文演讲遭佩洛西拒绝 特朗普：这是历史的污点】特朗普原定于29日在众议院发表演讲，然而佩洛西则以先开政府为前提要求特朗普推迟演讲。23日，特朗普在白宫正式对外宣布，他的国情咨文演讲被佩洛西取消了。他表示，佩洛西这么做是因为不想听真相，而这样的行为也足以成为历史的污点，而他将考虑其他方式发表演讲。","copyright":"","title":"国情咨文演讲遭佩洛西拒绝 特朗普：这是历史的污点","review":0,"author":"观察者网","mid":10330740,"created":1548296500,"length":"01:11","video_review":192,"aid":41538627,"bvid":"BV17t411b7VQ","hide_click":false,"is_pay":0,"is_union_video":0},{"comment":7040,"typeid":96,"play":810466,"pic":"//i2.hdslb.com/bfs/archive/4196ba338102960ab0603b7a69f44533e6449e54.jpg","subtitle":"","description":"当地时间23日下午，委内瑞拉总统马杜罗宣布与美国断交，并要求美使馆人员72小时内离开委内瑞拉。“我宣布与美帝国主义政府断绝所有外交和政治关系。滚！离开委内瑞拉。受够你们的干涉了，我们也是有尊严的！”","copyright":"","title":"断交！","review":0,"author":"观察者网","mid":10330740,"created":1548292703,"length":"01:09","video_review":1371,"aid":41535430,"bvid":"BV1jt411b7GH","hide_click":false,"is_pay":0,"is_union_video":0},{"comment":1416,"typeid":21,"play":126749,"pic":"//i1.hdslb.com/bfs/archive/360e9448968c68f39a71d786920dcecadaa38073.jpg","subtitle":"","description":"由于联邦政府部分关门，特朗普取消了整个美国代表团赴达沃斯论坛的行程。在1月22日的开幕式上，国务卿蓬佩奥通过视频连线发言。当大会主席布伦德半开玩笑地问他美国政府何时“开门”时，他先是干笑数声，然后表示：政治斗争是美国历史悠久的光荣传统，自己对于问题解决抱乐观态度","copyright":"","title":"蓬佩奥：政治斗争是美国历史悠久的光荣传统","review":0,"author":"观察者网","mid":10330740,"created":1548252500,"length":"00:33","video_review":220,"aid":41509329,"bvid":"BV1ut411b7AM","hide_click":false,"is_pay":0,"is_union_video":0},{"comment":719,"typeid":21,"play":88223,"pic":"//i2.hdslb.com/bfs/archive/663360bdca09092c4af4c5fe2564d552cc4bcabe.jpg","subtitle":"","description":"当地时间21日，荷兰瓦尔韦克市街头一男子突然发作，当街大吼并不断砸毁车辆。3名警员先后赶到与他对峙，期间使用了警棍与胡椒喷雾，由于男子反抗意识极强，警方先后被其打伤...最后不得不鸣枪示警，最终警方齐力将他抓获，目前案件正在调查中。","copyright":"","title":"真当自己超级赛亚人？荷兰男子街头砸车袭警被捕","review":0,"author":"观察者网","mid":10330740,"created":1548249390,"length":"01:54","video_review":325,"aid":41495653,"bvid":"BV1Gt411b7fn","hide_click":false,"is_pay":0,"is_union_video":0},{"comment":2086,"typeid":21,"play":183288,"pic":"//i0.hdslb.com/bfs/archive/87a2659d10245f2c07c933e713fd3b8a59b9f4f1.jpg","subtitle":"","description":"【美国最年轻女议员科特兹再抛惊人观点：世界将在12年内毁灭！】22日，美国最年轻民主党女议员科特兹再抛惊人观点：“如果我们不解决好气候变化问题，世界将在12年内毁灭，这是人类的第二次世界大战！”在谈到当前政治氛围时，科特兹表示，大家有必要一起“喷火”！去年11月，该位议员还曾因把美国的三权分立说错而受到网友群嘲。","copyright":"","title":"美国最年轻女议员科特兹再抛惊人观点：世界将在12年内毁灭！","review":0,"author":"观察者网","mid":10330740,"created":1548239324,"length":"01:24","video_review":730,"aid":41483598,"bvid":"BV1ft411t7zV","hide_click":false,"is_pay":0,"is_union_video":0},{"comment":714,"typeid":21,"play":122421,"pic":"//i1.hdslb.com/bfs/archive/fb66ae58c0ef5d0b9994e21b81e2894f01b012ed.jpg","subtitle":"","description":"1月21日，是美国黑人民权领袖马丁·路德·金纪念日。他的大儿子马丁·路德·金三世（Martin Luther King III）当天发表讲话，提到美国副总统彭斯日前将自己父亲金博士与特朗普相提并论，他激动得和演讲台一起跳了起来！","copyright":"","title":"说到特朗普 马丁·路德·金儿子和讲台一起跳了起来","review":0,"author":"观察者网","mid":10330740,"created":1548231333,"length":"01:15","video_review":235,"aid":41475575,"bvid":"BV1ot411t73g","hide_click":false,"is_pay":0,"is_union_video":0},{"comment":3329,"typeid":96,"play":235830,"pic":"//i0.hdslb.com/bfs/archive/93ffb2e1f0df71159bdc2f0bad2cac857ddbeeb4.jpg","subtitle":"","description":"22日，美国副总统彭斯在推特上发视频，公然煽动委内瑞拉人民反抗马杜罗政权，“我们与你们同在，我们支持你们”！随后，委内瑞拉副总统毫不客气地怼了回去：“美国佬滚回去！我们不会让你们干涉内政的！”","copyright":"","title":"公然煽动委内瑞拉人民“造反”，彭斯被骂惨了","review":0,"author":"观察者网","mid":10330740,"created":1548221648,"length":"02:22","video_review":1747,"aid":41463272,"bvid":"BV1At411b7jW","hide_click":false,"is_pay":0,"is_union_video":0},{"comment":3059,"typeid":21,"play":442566,"pic":"//i2.hdslb.com/bfs/archive/99f91cb83370e8188b467f033096e26a903ace9b.jpg","subtitle":"","description":"【美国政府持续关门 FBI特工：再不发工资我们就要跳槽了！】1月22日，甚少公开露面的FBI特工罕见召开新闻发布会呼吁政府开门向FBI拨款。FBI特工协会主席汤姆·奥康纳表示：“我已经听到一些年轻特工说，如果政府继续关门，他们就会考虑跳槽。一旦他们跳槽到私营企业，就会有相当于现在两到三倍的工资，你告诉我你会怎么做？”","copyright":"","title":"美国政府持续关门 FBI特工：再不发工资我们就要跳槽了！","review":0,"author":"观察者网","mid":10330740,"created":1548215644,"length":"01:44","video_review":1640,"aid":41455528,"bvid":"BV1ct411b7cN","hide_click":false,"is_pay":0,"is_union_video":0},{"comment":1467,"typeid":96,"play":418874,"pic":"//i0.hdslb.com/bfs/archive/a5f7515af980b76b6be69ba27ee47d52982898da.jpg","subtitle":"","description":"近日，RT挖出了一段伊拉克突击队训练的视频，子弹在脑袋和双腿间飞过……","copyright":"","title":"这段“伊拉克突击队训练视频”，过分硬核了啊","review":0,"author":"观察者网","mid":10330740,"created":1548214782,"length":"01:02","video_review":467,"aid":41453765,"bvid":"BV1ct411b7Pw","hide_click":false,"is_pay":0,"is_union_video":0},{"comment":1291,"typeid":96,"play":111168,"pic":"//i0.hdslb.com/bfs/archive/4cd2cbd5dbf215e7ea9ccd24486695b73ab91e06.jpg","subtitle":"","description":"当地时间22日，德国总理默克尔与法国总统马克龙在德国亚琛签署《亚琛条约》。该条约为1963年德法《爱丽舍宫条约》升级版，后者标志着二战后德法彻底和解，欧洲一体化的“法德轴心”正式形成。一方面，《亚琛条约》有望成为法德共同应对欧洲民粹主义和疑欧主义高涨的方案；另一方面，也有观点认为条约仅有象征意义，操作性不强。","copyright":"","title":"德法签署新条约，欧洲民粹要有麻烦了？","review":0,"author":"观察者网","mid":10330740,"created":1548210267,"length":"01:29","video_review":374,"aid":41450214,"bvid":"BV1St411t7LU","hide_click":false,"is_pay":0,"is_union_video":0},{"comment":3444,"typeid":21,"play":614624,"pic":"//i1.hdslb.com/bfs/archive/ce9d0f1f2b6745be779009f836a2629ddba66f5f.jpg","subtitle":"","description":"19日，从洛杉矶飞往台湾的航班上，一名200公斤白人男子以行动不便为由，要求空姐为其脱内裤。十多分钟后，他又让空姐帮他擦屁股。21日，当事空姐在新闻发布会上声泪俱下，控诉这段“可怕经历”，并且透露了这名乘客多次的黑历史。\n22日，@长荣航空EVAAIR 回应：公司已关怀并将视空服员之需求适切提供身心咨询协助；也将进一步调查该旅客是否涉及性骚扰行为，若该名旅客行为造成空服员伤害，公司将采取必要措施，避免类似情况再发生。","copyright":"","title":"200公斤白人男子要求空姐帮擦屁股，航空公司回应了","review":0,"author":"观察者网","mid":10330740,"created":1548144366,"length":"02:12","video_review":1591,"aid":41391078,"bvid":"BV1Wt411h78L","hide_click":false,"is_pay":0,"is_union_video":0},{"comment":722,"typeid":21,"play":166824,"pic":"//i1.hdslb.com/bfs/archive/1d33ec9915dd6ce51091bed1403fcc2c62678410.jpg","subtitle":"","description":"美国堪萨斯州一男子的拉布拉多走丢了，一家人找了一天愣是没找到。然而就在第二天男子准备放弃回家时狗子竟然自己跑回来了，而且身后还带着另一只狗和一只山羊...","copyright":"","title":"狗子丢了一夜 第二天竟带了2个朋友回家？？？","review":0,"author":"观察者网","mid":10330740,"created":1548141446,"length":"01:03","video_review":264,"aid":41386559,"bvid":"BV1pt411h7LK","hide_click":false,"is_pay":0,"is_union_video":0},{"comment":1628,"typeid":21,"play":135790,"pic":"//i2.hdslb.com/bfs/archive/b31410196760437da35fec6cf09310c30d52d63a.jpg","subtitle":"","description":"1月21日，民主党籍非裔参议员卡马拉•哈里斯宣布参加2020年美国总统大选。 哈里斯是首位宣布参加2020年大选的非裔美国女性，一旦当选，她将成为首位美国女性总统，和继奥巴马之后的第二位非裔总统。 就在宣布竞选几个小时前，她还发推“怼”了特朗普。不过，有民调显示，54%的民主党初选选民对哈里斯没有把握或从未听说过她。以下为她的参选视频↓","copyright":"","title":"“女版奥巴马”来了！","review":0,"author":"观察者网","mid":10330740,"created":1548135928,"length":"00:59","video_review":589,"aid":41379941,"bvid":"BV1ut411h7EK","hide_click":false,"is_pay":0,"is_union_video":0},{"comment":1412,"typeid":21,"play":162519,"pic":"//i1.hdslb.com/bfs/archive/7e52a80c9f4ca2c4e48160e20f462575a711ffae.jpg","subtitle":"","description":"19日，韩国一男子在公交车上玩弄刀具，还威胁旁边的乘客“离我远点”。一位女乘客赶紧发短信报警。没想到，警察赶到后并没有第一时间找到并控制持刀男子，反而高喊“谁报的警”，并不断给报警人打电话。报警女子因害怕没有回应，然后，警察就这么直接走了……","copyright":"","title":"韩国男子公交车上挥舞刀具，警察到场不抓人反而高喊……","review":0,"author":"观察者网","mid":10330740,"created":1548131525,"length":"01:04","video_review":189,"aid":41371713,"bvid":"BV1Kt411h7Q5","hide_click":false,"is_pay":0,"is_union_video":0},{"comment":1001,"typeid":21,"play":184005,"pic":"//i1.hdslb.com/bfs/archive/c0b30fb7c30cbdca6b6c8e0c24f563b7b3517787.jpg","subtitle":"","description":"【拖欠工资！建筑工人开着挖掘机就“杀”进来了】1月21日，英国利物浦一名建筑工人因被拖欠600英镑工资，一怒之下开着挖掘机“杀”进了拖欠其工资的酒店。据悉，该酒店是英国知名的连锁经济型酒店旅客之家，被撞后酒店内部装潢尽毁，门窗玻璃散落一地。事发当日正是装修工程交付完工之日。警方赶到现场时，涉事建筑工已经逃离了现场。目前，案件尚在调查中，事件未造成人员受伤。","copyright":"","title":"拖欠工资！建筑工人开着挖掘机就“杀”进来了","review":0,"author":"观察者网","mid":10330740,"created":1548125260,"length":"00:51","video_review":280,"aid":41366636,"bvid":"BV1Lt411h7ry","hide_click":false,"is_pay":0,"is_union_video":0},{"comment":1016,"typeid":96,"play":158883,"pic":"//i2.hdslb.com/bfs/archive/b80f3a284c69ba76bae6865dab8ddc16c6fe01a0.jpg","subtitle":"","description":"21日，塔利班驾驶装有自杀式炸弹的汽车，冲入阿富汗东部省一军事基地，随后双方交火。据路透社援引军方消息人士说法，爆炸已致126人死亡。袭击发生后，塔利班宣布恢复与美国的和平谈判。","copyright":"","title":"炸死100多名阿富汗人后，塔利班与美国和谈","review":0,"author":"观察者网","mid":10330740,"created":1548119999,"length":"00:56","video_review":129,"aid":41362002,"bvid":"BV15t411h7RU","hide_click":false,"is_pay":0,"is_union_video":0},{"comment":1794,"typeid":21,"play":370582,"pic":"//i2.hdslb.com/bfs/archive/f574e23c141d550d9014bd76029f70be10c2ab8b.jpg","subtitle":"","description":"当地时间18日，在泰国曼谷发生一起匪夷所思的暴力事件，一名贩卖护身符的店主与一位路过的僧人发生了口角，店主表示自己脖子上的护身符有神力，能逢凶化吉。“僧人”却不以为然，两人争执之间，这名“僧人”突然从袍间拔出一把近20厘米长刀割伤了店主的喉咙，店主顿时血流不止……然而幸运的是，店主在一名游客的帮助下等到了救援人员的到来，目前正在接受紧急治疗。","copyright":"","title":"为证明护身符无效 泰国“僧人”用长刀将店主抹喉","review":0,"author":"观察者网","mid":10330740,"created":1548078019,"length":"00:49","video_review":383,"aid":41334168,"bvid":"BV1Kt411h7F3","hide_click":false,"is_pay":0,"is_union_video":0},{"comment":4619,"typeid":96,"play":1103645,"pic":"//i0.hdslb.com/bfs/archive/f8c5fd390e576ca58954b0292541580ea0045616.jpg","subtitle":"","description":"近日，一段美国高中生“嘲笑”印第安越战老兵的视频，刷爆了美国社交媒体。从主流媒体，到政府官员，再到社交舆论场，几乎全在谴责这群戴MAGA帽子的高中生散播仇恨，同时声援遭到无礼对待的印第安越南老兵。然而，当其他现场视频浮出水面后，大家才发现是原住民主动接近学生……","copyright":"","title":"这个“对视”，让全美国怒了！……然后发现被耍了","review":0,"author":"观察者网","mid":10330740,"created":1548063881,"length":"03:31","video_review":2338,"aid":41311707,"bvid":"BV1mt41187Jw","hide_click":false,"is_pay":0,"is_union_video":0},{"comment":2777,"typeid":21,"play":444120,"pic":"//i1.hdslb.com/bfs/archive/975b9fb251d10001bdf4ac13a8285bfc0f642a0a.jpg","subtitle":"","description":"当地时间18日，美国佛罗里达州一对夫妇因涉嫌盗窃被警方当街逮捕。因怀疑两人有枪，警方全程武装并高度戒备。然而逮捕中途让人心碎的一幕发生了，两人2岁的女儿光着小脚独自走下车，高举双手走向警察。在场警员估计当时也没hold住，暂时解开了妈妈让她照顾这名女童。","copyright":"","title":"看到父母被抓 2岁的她高举双手走向警察","review":0,"author":"观察者网","mid":10330740,"created":1548053600,"length":"01:37","video_review":672,"aid":41299320,"bvid":"BV19t411874o","hide_click":false,"is_pay":0,"is_union_video":0}]},"page":{"count":6208,"pn":88,"ps":30}}}