{"code":0,"message":"0","ttl":1,"data":{"list":{"tlist":{"1":{"tid":1,"count":6,"name":"动画"},"119":{"tid":119,"count":2,"name":"鬼畜"},"129":{"tid":129,"count":3,"name":"舞蹈"},"155":{"tid":155,"count":6,"name":"时尚"},"160":{"tid":160,"count":3459,"name":"生活"},"165":{"tid":165,"count":5,"name":"广告"},"177":{"tid":177,"count":8,"name":"纪录片"},"181":{"tid":181,"count":69,"name":"影视"},"188":{"tid":188,"count":14,"name":"数码"},"3":{"tid":3,"count":19,"name":"音乐"},"36":{"tid":36,"count":2556,"name":"科技"},"4":{"tid":4,"count":9,"name":"游戏"},"5":{"tid":5,"count":52,"name":"娱乐"}},"vlist":[{"comment":293,"typeid":124,"play":25354,"pic":"//i1.hdslb.com/bfs/archive/777809d2bb8ca3ff86c740ab3dca7af32519a307.jpg","subtitle":"","description":"月底了，我猜你缺的不是锦鲤而是印钞机。","copyright":"","title":"月底了，给大家放个白纸变欧元的魔法视频吧","review":0,"author":"观察者网","mid":10330740,"created":1509432961,"length":"03:26","video_review":222,"aid":15892045,"bvid":"BV13x411E7Xb","hide_click":false,"is_pay":0,"is_union_video":0},{"comment":179,"typeid":124,"play":29458,"pic":"//i1.hdslb.com/bfs/archive/610991358cbdde61996ddb8e28e7976447d49a5a.jpg","subtitle":"","description":"那可真是美国鬼节\u0026gt;\u0026lt;","copyright":"","title":"第一次发现，希拉里还挺幽默的。。。","review":0,"author":"观察者网","mid":10330740,"created":1509431750,"length":"00:24","video_review":28,"aid":15891553,"bvid":"BV13x411E7yj","hide_click":false,"is_pay":0,"is_union_video":0},{"comment":481,"typeid":39,"play":37953,"pic":"//i2.hdslb.com/bfs/archive/c5a884f652c923459bbba50299e2e2a52b7bb919.jpg","subtitle":"","description":"本期，观天下讲坛特邀华东师范大学法学院教授、《林肯传》译者田雷老师，为大家解读“假如林肯还活着，会如何看待美国当下的文化内战？”。\n\n田雷，华东师范大学法学院教授，《雅理译丛》主编。香港中文大学政治学博士（2008年），耶鲁大学法学硕士（2010年）。研究方向主要包括：美国宪法的历史与理论、中国政治与宪法、香港特别行政区基本法以及政治理论。近期出版的译著包括《林肯传》和《我们的孩子》。","copyright":"","title":"【观天下讲坛第12期】田雷：假如林肯还活着，会如何看待美国当下的文化内战？","review":0,"author":"观察者网","mid":10330740,"created":1509414284,"length":"79:16","video_review":1417,"aid":15885568,"bvid":"BV13x411E7Go","hide_click":false,"is_pay":0,"is_union_video":0},{"comment":710,"typeid":124,"play":50870,"pic":"//i2.hdslb.com/bfs/archive/64f74b1deadafd8c38cc57fcb41c4d8db617c8df.jpg","subtitle":"","description":"还好有监控！","copyright":"","title":"俄83岁老妇差点遭诈骗，报警后却真被警察给偷了……","review":0,"author":"观察者网","mid":10330740,"created":1509359601,"length":"01:46","video_review":74,"aid":15870580,"bvid":"BV1Lx411E7Dx","hide_click":false,"is_pay":0,"is_union_video":0},{"comment":364,"typeid":96,"play":25567,"pic":"//i2.hdslb.com/bfs/archive/d299e59800b6e2048871f328cba5f13746e1d3dc.jpg","subtitle":"","description":"据《今日印度》10月6日报道，一架印度空军Mi-17运输直升机当地时间6日6时在中印边境地区坠毁，所有7名乘员死亡。据最新曝光的一段视频，一个空投油罐的降落伞与直升机的尾翼缠住，导致尾翼从机上掉落，直升机随即失控并坠毁。","copyright":"","title":"印度空军直升机坠毁视频曝光 揭露坠毁原因","review":0,"author":"观察者网","mid":10330740,"created":1509357255,"length":"00:22","video_review":43,"aid":15869679,"bvid":"BV1jx411E7KZ","hide_click":false,"is_pay":0,"is_union_video":0},{"comment":154,"typeid":75,"play":29394,"pic":"//i0.hdslb.com/bfs/archive/606042c923db75b7b66512433e42ad905f856ab4.jpg","subtitle":"","description":"总有一天，我会有猫的！","copyright":"","title":"感人…终于找到了溜猫的正确姿势！","review":0,"author":"观察者网","mid":10330740,"created":1509354393,"length":"00:54","video_review":62,"aid":15868248,"bvid":"BV1jx411E7He","hide_click":false,"is_pay":0,"is_union_video":0},{"comment":269,"typeid":124,"play":66330,"pic":"//i2.hdslb.com/bfs/archive/cb376409eced49324eb358ca6dceca431468efcc.jpg","subtitle":"","description":"滴，观察动物卡","copyright":"","title":"洋葱社讯：美民众在垃圾箱内发现两俄罗斯间谍！","review":0,"author":"观察者网","mid":10330740,"created":1509256072,"length":"01:21","video_review":146,"aid":15832035,"bvid":"BV1Nx411E7ah","hide_click":false,"is_pay":0,"is_union_video":0},{"comment":1734,"typeid":21,"play":1295238,"pic":"//i1.hdslb.com/bfs/archive/1a735db38f1cddad9d4b8d671745707d81c9b0d5.jpg","subtitle":"","description":"宝宝妈妈的胜负心很重啊哈哈。相比起去年一脸委屈，今年她已经笑着说“有一个同学哭了耶”","copyright":"","title":"去年万圣节吓哭同学的小朋友今年又来了……","review":0,"author":"观察者网","mid":10330740,"created":1509250797,"length":"00:36","video_review":1276,"aid":15830159,"bvid":"BV1Ax411E73g","hide_click":false,"is_pay":0,"is_union_video":0},{"comment":2791,"typeid":21,"play":901993,"pic":"//i1.hdslb.com/bfs/archive/c9f32438d430617039536fff14ee98aa6d08e309.jpg","subtitle":"","description":"10月25日，海南海口有两名男子合伙偷外卖，在偷第二份时被发现，其中一名嫌疑人见形势不妙，迅速逃离了现场，另一名嫌疑人试图逃跑时，则被外卖小哥一路狂追扑倒。网友：外卖员是继朝阳群众后，又一个神秘组织~","copyright":"","title":"继朝阳群众之后，外卖小哥可能也是个神秘组织~","review":0,"author":"观察者网","mid":10330740,"created":1509177949,"length":"00:56","video_review":981,"aid":15801450,"bvid":"BV19x41177rx","hide_click":false,"is_pay":0,"is_union_video":0},{"comment":711,"typeid":138,"play":734829,"pic":"//i1.hdslb.com/bfs/archive/ad740a041709017f2c9ab9f52d2220bbb4b114fd.jpg","subtitle":"","description":"在位于美国华盛顿的国际间谍博物馆，一名游客体验馆内特色互动虚拟“鲨鱼缸”，“鱼缸”顶上写着：触摸后果自负。结尾高能，一定要看到最后！","copyright":"","title":"触摸“鲨鱼缸” 后果自负……一定要看到最后！","review":0,"author":"观察者网","mid":10330740,"created":1509094952,"length":"00:25","video_review":339,"aid":15769592,"bvid":"BV1yx41177ML","hide_click":false,"is_pay":0,"is_union_video":0},{"comment":2056,"typeid":201,"play":263935,"pic":"//i0.hdslb.com/bfs/archive/bf6a3f1930a56b0689840f6a6dfa52840a038301.jpg","subtitle":"","description":"据报道10月25日，在利雅得未来投资倡议论坛上，沙特授予类人机器人索菲亚(Sophia)该国公民身份。索菲亚展示了自己的面部表情功能，并表示想用自己的人工智能来帮助人类过上更好的生活。去年，她曾宣称要毁灭人类而登上新闻头条。","copyright":"","title":"曾称要毁灭人类的她 成为全世界首个机器人公民！","review":0,"author":"观察者网","mid":10330740,"created":1509080402,"length":"01:09","video_review":485,"aid":15763023,"bvid":"BV1Cx41177bb","hide_click":false,"is_pay":0,"is_union_video":0},{"comment":111,"typeid":174,"play":8602,"pic":"//i2.hdslb.com/bfs/archive/c4d9f418e91146a07653244992bfa77ec0351a5b.jpg","subtitle":"","description":"2017年10月20日，交响合唱《启航》作为上海国际艺术节开幕作品，进行世界首演观众反响热烈。我们找到了《启航》创作者——上海爱乐乐团驻团作曲家龚天鹏，与他聊了作品背后的故事……","copyright":"","title":"对话上海国际艺术节《启航》作者龚天鹏：这就是我想讲的“中国故事”","review":0,"author":"观察者网","mid":10330740,"created":1509012241,"length":"02:02","video_review":36,"aid":15742771,"bvid":"BV1qx4117785","hide_click":false,"is_pay":0,"is_union_video":0},{"comment":688,"typeid":75,"play":35497,"pic":"//i0.hdslb.com/bfs/archive/9a8da4a1e125800ae1b4f99aef470d8090f21945.jpg","subtitle":"","description":"台北市立动物园回应：活动户外新栽种了几棵树，为避免大熊猫攀爬，导致新树无法存活，才架上电网。虽然团团圆圆都被电过，但绝没有吓到不愿出栏舍，只是户外活动时会避开这几棵树。","copyright":"","title":"台北巿立动物园架电网，团团圆圆都中招误触电","review":0,"author":"观察者网","mid":10330740,"created":1509007660,"length":"00:41","video_review":186,"aid":15740916,"bvid":"BV1vx41177qT","hide_click":false,"is_pay":0,"is_union_video":0},{"comment":561,"typeid":137,"play":12689,"pic":"//i1.hdslb.com/bfs/archive/3e3fc20cc3bceb9e3cde88d3aed3b052abab0a00.jpg","subtitle":"","description":"刘亦菲凭《三生三世十里桃花》“白浅”一角获东京电影节中国电影周“金鹤奖”最佳女主角，初代HelloKitty设计者清水女士揭晓奖项。刘亦菲发视频表达感谢。2016年吴亦凡凭《夏有乔木雅望天堂》获得“金鹤奖”最佳男主角。","copyright":"","title":"刘亦菲获东京电影节中国电影周“金鹤奖”最佳女主角","review":0,"author":"观察者网","mid":10330740,"created":1509006827,"length":"01:02","video_review":127,"aid":15740408,"bvid":"BV1vx41177tN","hide_click":false,"is_pay":0,"is_union_video":0},{"comment":155,"typeid":21,"play":13008,"pic":"//i2.hdslb.com/bfs/archive/3b22bff446cbed4a6732f732402a6de936b4510c.jpg","subtitle":"","description":"英国冒险家用100个氦气球绑在露营椅上，在南非约翰内斯堡升空，飞行25公里，最高达到8000英尺（2438米）。平安落地后，汤姆·摩根表示这绝对是地球上最棒的冒险！旅程非常美妙，兴奋与恐惧并存！","copyright":"","title":"飞椅环游记？英国冒险家100个气球绑椅子 飞上2.5千米高空","review":0,"author":"观察者网","mid":10330740,"created":1508991768,"length":"01:11","video_review":74,"aid":15734720,"bvid":"BV1vx41177Ft","hide_click":false,"is_pay":0,"is_union_video":0},{"comment":1514,"typeid":124,"play":799876,"pic":"//i1.hdslb.com/bfs/archive/eda863f265aa74b800fbb1fda4c1b491836e3165.jpg","subtitle":"","description":"该视频由@CGTNWorldInsight授权发布。","copyright":"","title":"外媒是否如实报道了中国？来，这题让CNN记者回答一下","review":0,"author":"观察者网","mid":10330740,"created":1508988983,"length":"01:00","video_review":0,"aid":15733603,"bvid":"BV1vx41177nS","hide_click":false,"is_pay":0,"is_union_video":0},{"comment":1517,"typeid":96,"play":31593,"pic":"//i0.hdslb.com/bfs/archive/c78a5c621537d57586e68647760617ccfeb3df52.jpg","subtitle":"","description":"美国政府曾指责童婚“侵犯人权”并导致其他社会问题，也严厉谴责其他国家的童婚现象，但在美国，童婚却大量存在。据BBC报道，美国50个州都允许18岁以下未成年结婚。2000至2015年间，美国有超20万未成年人结婚。安吉尔被迫在13岁结婚，并在15岁生下孩子，丈夫在她怀孕期间虐待她；谢丽在11岁时被强奸后怀孕，最后还要嫁给强奸犯，现在她致力于游说以修改当地法律。","copyright":"","title":"美国童婚泛滥 50个州都允许18岁以下童婚","review":0,"author":"观察者网","mid":10330740,"created":1508918335,"length":"04:09","video_review":453,"aid":15712764,"bvid":"BV15x411u72N","hide_click":false,"is_pay":0,"is_union_video":0},{"comment":1464,"typeid":137,"play":125205,"pic":"//i2.hdslb.com/bfs/archive/561f265613d7e1828ccff4be952014b79e0fa69a.jpg","subtitle":"","description":"10月23日，四位中国青年代表就如何消除公众对艾滋病的歧视及污名化进行讨论。现场当易烊千玺发言时，bernhard schwartlander博士戴上同声传译耳机，但听到易烊千玺用英文发言时，随即摘下耳机微笑看向身边这位中国小伙。","copyright":"","title":"易烊千玺亮相日内瓦世卫总部 英文演讲现场【双语字幕版】","review":0,"author":"观察者网","mid":10330740,"created":1508825722,"length":"01:23","video_review":387,"aid":15682510,"bvid":"BV1Px411u7eJ","hide_click":false,"is_pay":0,"is_union_video":0},{"comment":309,"typeid":163,"play":65139,"pic":"//i2.hdslb.com/bfs/archive/1ab0718aebe3475ed91110e7ae0e3eab123a82dd.jpg","subtitle":"","description":"10月21日，泰国一场球赛中，两支队伍点球大战踢至19平，关键一球踢飞后，门将兴奋地庆祝胜利，没想到……这个故事告诉我们：别高兴的太早，以及真的会有奇迹。（也许是最不可思议的点球之一）","copyright":"","title":"这个故事告诉我们：别高兴的太早/真的会有奇迹","review":0,"author":"观察者网","mid":10330740,"created":1508816597,"length":"00:37","video_review":203,"aid":15679323,"bvid":"BV1Gx411u7UQ","hide_click":false,"is_pay":0,"is_union_video":0},{"comment":1081,"typeid":96,"play":85509,"pic":"//i0.hdslb.com/bfs/archive/2e2e1e8f30f7193a7c563bbd88c63f47926897c4.jpg","subtitle":"","description":"英国媒体公司KJ VIDS制作视频，描述当代中国发展水平。2005年时，中国人每两周就能建起一个如今的罗马，到了2015年，中国每16周增长的经济就相当于一个希腊，每25周就相当于一个以色列。","copyright":"","title":"建成罗马需要多久？中国人只需要两周！","review":0,"author":"观察者网","mid":10330740,"created":1508751351,"length":"08:23","video_review":1672,"aid":15659410,"bvid":"BV1Zx411M7oi","hide_click":false,"is_pay":0,"is_union_video":0},{"comment":188,"typeid":174,"play":30412,"pic":"//i1.hdslb.com/bfs/archive/107f153c26c861f8b3ab27667cdcf0fe7a4ef74b.jpg","subtitle":"","description":"印巴边境的降旗仪式被列为两国游客必看的项目之一，每天日落前准时在瓦嘎边境举行。仪式上双方士兵慷慨激昂，看台观众集体欢呼，热情高涨。","copyright":"","title":"实拍：印巴边境降旗仪式双方士兵“吹胡子瞪眼” 互斗士气","review":0,"author":"观察者网","mid":10330740,"created":1508747519,"length":"01:16","video_review":103,"aid":15658277,"bvid":"BV1dx411M7XM","hide_click":false,"is_pay":0,"is_union_video":0},{"comment":1219,"typeid":96,"play":111411,"pic":"//i1.hdslb.com/bfs/archive/c0693ff077bc0752a7f95c9fae4d1f3e3b29bcd9.jpg","subtitle":"","description":"【采访不成，照样把自己打成“焦点牌”，西方记者怎么做到的？】皱眉，叹气，耸肩，这成了某西方媒体记者在报道中国重大政治新闻时，受访要求屡遭拒绝后上演的戏码。还没来得及反思，这条“抓马”的报道已在其官网备受关注。然而，这一出讽刺的又是谁？@刘欣CGTN 为你一语道破！","copyright":"","title":"“戏精”西方记者是如何给自己加戏的？","review":0,"author":"观察者网","mid":10330740,"created":1508554752,"length":"03:37","video_review":619,"aid":15581274,"bvid":"BV1ex411M71H","hide_click":false,"is_pay":0,"is_union_video":0},{"comment":546,"typeid":98,"play":243689,"pic":"//i1.hdslb.com/bfs/archive/2ee7ed61cefc13d9756e381bce6ac12b94e77a23.jpg","subtitle":"","description":"10月8日，巴基斯坦拉合尔“橙线”项目举行接车仪式。“橙线”是中巴经济走廊的重要项目之一，此次接车仪式意味着巴基斯坦将进入地铁时代。此条视频实地拍摄了“橙线”的“中国造”地铁内外观。","copyright":"","title":"实拍巴铁兄弟迎来首列“中国造”地铁 戴小黄花徐徐驶入","review":0,"author":"观察者网","mid":10330740,"created":1508484250,"length":"00:53","video_review":256,"aid":15556836,"bvid":"BV14x411M7x8","hide_click":false,"is_pay":0,"is_union_video":0},{"comment":1612,"typeid":96,"play":177132,"pic":"//i1.hdslb.com/bfs/archive/05e875b5a63d1f3a1da87e89a3a29d90c6d7c949.jpg","subtitle":"","description":"叙利亚民主力量和“反伊斯兰国联盟”解放拉卡的主要军事行动接近完成，随着拉卡被解放，满目疮痍的广场上出现了庆祝的人群，妇女们也脱掉身上的黑色长袍，欢呼舞蹈...","copyright":"","title":"伊斯兰国首都”被解放，妇女脱黑袍狂喜舞蹈！","review":0,"author":"观察者网","mid":10330740,"created":1508406309,"length":"01:45","video_review":858,"aid":15534529,"bvid":"BV1bx411M7JG","hide_click":false,"is_pay":0,"is_union_video":0},{"comment":586,"typeid":71,"play":101678,"pic":"//i1.hdslb.com/bfs/archive/d52131fac98b71b37c4b433f28efd312631d5ce4.jpg","subtitle":"","description":"日本两男上《亚洲达人秀》，表演用肚子撞出声效。哈哈！怕是对才艺有什么误解！网友感叹“大肚男的时代到啦”。","copyright":"","title":"嘘~~~“啵”~~~哈哈哈~~~","review":0,"author":"观察者网","mid":10330740,"created":1508393628,"length":"05:12","video_review":840,"aid":15528867,"bvid":"BV1Ex411M7up","hide_click":false,"is_pay":0,"is_union_video":0},{"comment":323,"typeid":96,"play":34391,"pic":"//i0.hdslb.com/bfs/archive/4ab051531150936f284b19c0c822caf12e2f6d46.jpg","subtitle":"","description":"伊朗嘉宾：美国政府的态度反复无常，一会儿支持一会儿又全盘推翻。现在与美国和美国的盟国关系不佳的几个中东地区国家也门、卡塔尔、土耳其都投靠了伊朗，这真的不能怪伊朗，都怪美国这个麻烦制造者。\n美国专家：重谈伊朗核协议是不切实际的，这是华盛顿政府的共识，寻思退出伊朗核协议的只有特朗普自个儿，我们也不知道他到底咋想的。\n\n本视频由CGTNWorldInsight授权发布。","copyright":"","title":"伊朗专家批美国是个麻烦制造者 美国专家直言看不懂特朗普","review":0,"author":"观察者网","mid":10330740,"created":1508392687,"length":"02:30","video_review":87,"aid":15528709,"bvid":"BV1Ex411M73M","hide_click":false,"is_pay":0,"is_union_video":0},{"comment":165,"typeid":96,"play":23641,"pic":"//i0.hdslb.com/bfs/archive/c255899c3b7ee49682ed24f68f0f027d30a4d3f5.jpg","subtitle":"","description":"10月14日，美国印第安纳州安德森高速赛道上，两辆赛车相撞。被撞司机为报复直接驾车碾压对方车辆，而被压的司机逃出后也不甘示弱，两人大打出手，最后被赶来的警察双双逮捕。所以说，路怒要不得啊……","copyright":"","title":"真·速度与激情!? 两赛车相撞 司机直接碾压对方车辆","review":0,"author":"观察者网","mid":10330740,"created":1508322175,"length":"01:07","video_review":61,"aid":15509950,"bvid":"BV1Hx411M7w2","hide_click":false,"is_pay":0,"is_union_video":0},{"comment":760,"typeid":39,"play":20366,"pic":"//i2.hdslb.com/bfs/archive/acf9b2624a0e2c344d71e0c7f0ba283d3e4fac0e.jpg","subtitle":"","description":"【观天下讲坛第12期】\n《假如林肯还活着，会如何看到美国当下的文化内战》；\n主讲人：田雷；\n时间：10月22日14:30 B站\u0026amp;amp;amp;amp;amp;微博同步直播；\n详细信息：http://www.huodongxing.com/event/4409744825000","copyright":"","title":"【观天下讲坛12预告】假如林肯还活着，会如何看待美国当下的文化内战","review":0,"author":"观察者网","mid":10330740,"created":1508321914,"length":"04:30","video_review":320,"aid":15509726,"bvid":"BV1nx411M7dk","hide_click":false,"is_pay":0,"is_union_video":0},{"comment":515,"typeid":39,"play":53825,"pic":"//i1.hdslb.com/bfs/archive/cadd260b9fc06e3b2d7d1665e72ea5f7bbcfcfbe.jpg","subtitle":"","description":"好的爸爸！","copyright":"","title":"受梅德韦杰夫邀请参加俄罗斯论坛 马云：互联网比石油重要","review":0,"author":"观察者网","mid":10330740,"created":1508319569,"length":"02:10","video_review":229,"aid":15508667,"bvid":"BV1Hx411M7Ld","hide_click":false,"is_pay":0,"is_union_video":0},{"comment":247,"typeid":75,"play":39101,"pic":"//i2.hdslb.com/bfs/archive/a2292f83e522221e26249c4e996e56dcd831790e.jpg","subtitle":"","description":"终于想起来自己的“正业” ฅ^•ﻌ•^ฅ","copyright":"","title":"像狗狗一样玩叼树枝的狮子？怕不是个假大猫吧！","review":0,"author":"观察者网","mid":10330740,"created":1508237111,"length":"02:07","video_review":237,"aid":15484319,"bvid":"BV1Px411M77g","hide_click":false,"is_pay":0,"is_union_video":0}]},"page":{"count":6208,"pn":166,"ps":30}}}