{"code":0,"message":"0","ttl":1,"data":{"list":{"tlist":{"1":{"tid":1,"count":6,"name":"动画"},"119":{"tid":119,"count":2,"name":"鬼畜"},"129":{"tid":129,"count":3,"name":"舞蹈"},"155":{"tid":155,"count":6,"name":"时尚"},"160":{"tid":160,"count":3459,"name":"生活"},"165":{"tid":165,"count":5,"name":"广告"},"177":{"tid":177,"count":8,"name":"纪录片"},"181":{"tid":181,"count":69,"name":"影视"},"188":{"tid":188,"count":14,"name":"数码"},"3":{"tid":3,"count":19,"name":"音乐"},"36":{"tid":36,"count":2556,"name":"科技"},"4":{"tid":4,"count":9,"name":"游戏"},"5":{"tid":5,"count":52,"name":"娱乐"}},"vlist":[{"comment":2681,"typeid":124,"play":713672,"pic":"//i1.hdslb.com/bfs/archive/2e0d5336592b134f24a0792fa2f22f3690117791.jpg","subtitle":"","description":"2014年盐湖城，一位名叫siale angilau的25岁黑帮份子，在自己被起诉的法庭上抄起了辩护律师的笔，试图袭击目击证人。法警见状连开四枪，当场将袭击者击毙。","copyright":"","title":"美国黑帮份子法庭突然抢笔袭击证人，法警连开四枪当场将其击毙","review":0,"author":"观察者网","mid":10330740,"created":1520946849,"length":"00:27","video_review":415,"aid":20734600,"bvid":"BV1FW411p7kk","hide_click":false,"is_pay":0,"is_union_video":0},{"comment":361,"typeid":124,"play":16032,"pic":"//i2.hdslb.com/bfs/archive/6d4e0c1a08603f4b8bca21b3a68820f674d9b557.jpg","subtitle":"","description":"从1989年开始，美国政府会在首都华盛顿特区的国会大厦西草坪举行阵亡将士纪念日音乐节。各军种的高级指挥官都会出席音乐会。而各军种的军歌奏响时，曾经在该军种中服役的人就会起立致敬并高唱军歌。","copyright":"","title":"2017年美国阵亡将士纪念日音乐会","review":0,"author":"观察者网","mid":10330740,"created":1520937760,"length":"04:59","video_review":283,"aid":20726233,"bvid":"BV1ZW411H7gz","hide_click":false,"is_pay":0,"is_union_video":0},{"comment":1674,"typeid":21,"play":146560,"pic":"//i0.hdslb.com/bfs/archive/dba11925e38ffcedfafd69cfddc01ed22ecd043b.jpg","subtitle":"","description":"3月12日的议会上，首相特蕾莎·梅和议员们就俄罗斯毒害双面间谍事件炮轰俄罗斯，俄罗斯回应这是一场“马戏表演”。","copyright":"","title":"为双面间谍中毒这事 英议会开了场“骂俄罗斯”大赛","review":0,"author":"观察者网","mid":10330740,"created":1520930102,"length":"02:23","video_review":1190,"aid":20723870,"bvid":"BV1KW411p7wx","hide_click":false,"is_pay":0,"is_union_video":0},{"comment":345,"typeid":21,"play":51892,"pic":"//i1.hdslb.com/bfs/archive/5a621ead775b456e9e51b0c8bcf5a0c78e2379b5.jpg","subtitle":"","description":"3月10日，俄罗斯克拉斯诺亚尔斯克的一辆公交车突然起火，而就在几米外的小伙儿依旧淡定的吃着饭！","copyright":"","title":"分享一个战斗民族吃货的日常~","review":0,"author":"观察者网","mid":10330740,"created":1520929902,"length":"00:32","video_review":85,"aid":20724089,"bvid":"BV1KW411p7M4","hide_click":false,"is_pay":0,"is_union_video":0},{"comment":804,"typeid":201,"play":37909,"pic":"//i2.hdslb.com/bfs/archive/c267326718edc8939fe0801a97b25582dff6e9a0.jpg","subtitle":"","description":"https://pjmedia.com/video/elon-musk-warns-first-travelers-to-mars-good-chance-youll-die/\n【太空漫游即将实现？创始人却说乘客很可能送死】11 日在德州举办的西南偏南大会（SXSW）上，马斯克透露SpaceX 正在打造第一艘太空船，预计明年上半年度就能开始短程飞行测试。不过他说：这很危险，做好死亡的准备吧！","copyright":"","title":"马斯克：正在制造送人到火星的飞船，乘客要做好送死的准备","review":0,"author":"观察者网","mid":10330740,"created":1520915384,"length":"00:48","video_review":91,"aid":20716598,"bvid":"BV1AW411p7nx","hide_click":false,"is_pay":0,"is_union_video":0},{"comment":552,"typeid":96,"play":63610,"pic":"//i2.hdslb.com/bfs/archive/1eed8b597b2ae322a9d01584ee971b1e20e11e61.jpg","subtitle":"","description":"西方专家说俄罗斯“秀肌肉”是宣告新冷战，普京这样回应","copyright":"","title":"西方专家说俄罗斯“秀肌肉”是宣告新冷战，普京这样回应","review":0,"author":"观察者网","mid":10330740,"created":1520913849,"length":"02:13","video_review":189,"aid":20715675,"bvid":"BV1AW411p7iK","hide_click":false,"is_pay":0,"is_union_video":0},{"comment":1149,"typeid":39,"play":163154,"pic":"//i0.hdslb.com/bfs/archive/da58d795833aa259aa751bf1b33c00cad228b5ff.jpg","subtitle":"","description":"凯利：你是不是说美国干涉了俄罗斯大选\n普京：是\n凯利：但俄罗斯没有干涉美国大选？\n普京：没有\n凯利：为什么没有干涉？\n普京：没法干涉\n凯利：我不信，你们肯定搞网络战\n普京：我们没有CNN\n凯利：可是你们有导弹啊\n观众：？？？\n（距离2016美国大选已经过去很久很久了，特朗普都宣布2020竞选口号了……\nhttps://www.youtube.com/watch?v=9mhi_AyQAyw\u0026t=2367s","copyright":"","title":"NBC专访普京的这段对话是在搞笑吗？？","review":0,"author":"观察者网","mid":10330740,"created":1520908285,"length":"01:54","video_review":632,"aid":20712738,"bvid":"BV1wW411p7Gx","hide_click":false,"is_pay":0,"is_union_video":0},{"comment":1319,"typeid":21,"play":43497,"pic":"//i0.hdslb.com/bfs/archive/43e3e036a0737f68626f5e9d2c84cca895143a8f.jpg","subtitle":"","description":"3万多名来自印度马哈拉施特拉邦的农民经过5天长达180公里的徒步游行，于3月12日到达重要城市孟买，继续表达他们的诉求。\n印度共产党（马列）新民主的分支（AIKS）和其他农会组织联合举行了这次游行。\n他们的诉求包括要求政府无条件豁免贷款并提高农产品价格。\n由于气候干旱，不少印度农民处境艰难，虽然国家已经宣布了一项贷款减免计划，但实施情况参差不齐。","copyright":"","title":"印度三万多农民展开徒步远行集会 要求获得贷款豁免","review":0,"author":"观察者网","mid":10330740,"created":1520862300,"length":"00:41","video_review":168,"aid":20697702,"bvid":"BV18W411s7BW","hide_click":false,"is_pay":0,"is_union_video":0},{"comment":194,"typeid":21,"play":10184,"pic":"//i2.hdslb.com/bfs/archive/d9985971cefb1c1c297dc53b9e4bd84983c6595e.jpg","subtitle":"","description":"外媒3月12日消息，尼泊尔加德满都机场发生一起坠机事件，可以看到现场浓烟滚滚。另据路透社最新消息，尼泊尔军方发言人称，坠机已致至少50人死亡。","copyright":"","title":"一架载有71人的客机在尼伯尔降落时起火 17人受伤其余恐遇难","review":0,"author":"观察者网","mid":10330740,"created":1520861830,"length":"00:30","video_review":20,"aid":20697739,"bvid":"BV18W411s7ih","hide_click":false,"is_pay":0,"is_union_video":0},{"comment":1295,"typeid":96,"play":108041,"pic":"//i1.hdslb.com/bfs/archive/ae563166afb39a28b35fd2e3800c322a65dea57f.jpg","subtitle":"","description":"普京接受美国NBC电视台主播摩根·凯利专访，第N次谈到“通俄门”，面对美国记者喋喋不休的追问，普京提起不久前与美国高层的一次对话，他们毫不掩饰自己干涉俄罗斯政治，并且理直气壮：我们是在传播民主啊","copyright":"","title":"普京:美国高层对我说，干涉俄罗斯内政是在传播民主","review":0,"author":"观察者网","mid":10330740,"created":1520850559,"length":"01:03","video_review":159,"aid":20691770,"bvid":"BV1qW411s7sD","hide_click":false,"is_pay":0,"is_union_video":0},{"comment":1055,"typeid":21,"play":54159,"pic":"//i1.hdslb.com/bfs/archive/3da2d9967e77b81e74a4e8add44ba60c2403e06e.jpg","subtitle":"","description":"来自中国香港的Fiona毕业于英国安格里亚鲁斯金大学国际商业战略专业。但毕业后的她找工作困难，认为自己拿到了毫无价值的“米老鼠学位”，几经向校方投诉无果后她选择了起诉母校，要求赔偿包括两年学费和生活费在内的6万英镑（约合人民币52万）","copyright":"","title":"毕业才发现真相，“米老鼠学位”留学生起诉英国大学要求赔偿52万","review":0,"author":"观察者网","mid":10330740,"created":1520848770,"length":"02:05","video_review":217,"aid":20687799,"bvid":"BV1iW411s7gG","hide_click":false,"is_pay":0,"is_union_video":0},{"comment":149,"typeid":75,"play":13742,"pic":"//i1.hdslb.com/bfs/archive/cc638a8eb62c661d12caafb3a72213e54be672e9.jpg","subtitle":"","description":"【小海龟，用它们自己的方式倔犟的回到海洋】摄影师Morgin 奥利弗记录了一段小海龟奋力爬回海洋的过程。母海龟会在陆地上产卵，小海龟孵化出来后，会自己摆动着小小的身体重新回归海洋，这个过程对它们来说就是人生的第一次冒险！","copyright":"","title":"小海龟，用它们自己的方式倔犟的回到海洋","review":0,"author":"观察者网","mid":10330740,"created":1520841470,"length":"00:59","video_review":50,"aid":20685683,"bvid":"BV1iW411s7mY","hide_click":false,"is_pay":0,"is_union_video":0},{"comment":171,"typeid":21,"play":24802,"pic":"//i1.hdslb.com/bfs/archive/a06311295879885cae5ccdc1ea36cb5dc02b9706.jpg","subtitle":"","description":"加利福尼亚州一笨贼闯入动物收容所，只为了偷一个糖果机...","copyright":"","title":"糖果机究竟做错了什么 为什么要这么对它","review":0,"author":"观察者网","mid":10330740,"created":1520837726,"length":"01:21","video_review":67,"aid":20685120,"bvid":"BV1iW411s7B8","hide_click":false,"is_pay":0,"is_union_video":0},{"comment":865,"typeid":39,"play":84478,"pic":"//i0.hdslb.com/bfs/archive/4e0ac33114e6b816faecf94edcc6fbbe6b2c2669.jpg","subtitle":"","description":"普京接受NBC专访，在谈到特朗普时，普京称其务实、领导力强，但NBC播出的版本不仅删减了大段回答，英文翻译也直接篡改了普京的原意。我们对比了NBC和克里姆林宫两个版本，字幕为克宫版本，与NBC翻译有较大出入。附删减片段。","copyright":"","title":"普京接受美媒专访时夸特朗普 但播出时却…没了？（附删减片段）","review":0,"author":"观察者网","mid":10330740,"created":1520837624,"length":"02:40","video_review":191,"aid":20684584,"bvid":"BV1eW411s7rL","hide_click":false,"is_pay":0,"is_union_video":0},{"comment":156,"typeid":96,"play":153405,"pic":"//i1.hdslb.com/bfs/archive/55fa99051a65664fd8b210289c784f5dd0c97208.jpg","subtitle":"","description":"https://news.ftv.com.tw/news/detail/2018311P04M1\n【为强化维安，台湾“总统府”将设“景观围篱”】台湾“总统府”维安事件频发，为加强治安，“总统府”将加设景观围篱，并为安保人员配备“网枪”，能将对方绊倒后再进行电击。","copyright":"","title":"维安事件频发，台湾“总统府”这次架起了高高的围栏","review":0,"author":"观察者网","mid":10330740,"created":1520835365,"length":"00:48","video_review":24,"aid":20683651,"bvid":"BV1eW411s7o5","hide_click":false,"is_pay":0,"is_union_video":0},{"comment":619,"typeid":96,"play":164415,"pic":"//i0.hdslb.com/bfs/archive/7ad75a5c618c7ed02691d6156debde83cd3e0662.jpg","subtitle":"","description":"普京：索契冬奥会开幕式闹乌龙，差点打下一架客机","copyright":"","title":"普京：索契冬奥会开幕式闹乌龙，差点打下一架客机","review":0,"author":"观察者网","mid":10330740,"created":1520832686,"length":"03:24","video_review":402,"aid":20681587,"bvid":"BV1vW411s7ed","hide_click":false,"is_pay":0,"is_union_video":0},{"comment":344,"typeid":75,"play":87558,"pic":"//i2.hdslb.com/bfs/archive/f68a2e9babbc4da1059fa221f2e86fb72f419a8f.jpg","subtitle":"","description":"https://youtu.be/7Vw69fdItBg\n【柴犬当新闻主播，萌翻了！】日本有一只名为“犬山柴男”的狗狗一本正经地坐在演播厅中，当起了“新闻主播”。虽然犬山柴男全程一言未发，但躺在主播台上呼呼大睡的模样萌翻了观众。网友调侃：这档新闻节目我看一天都不腻！","copyright":"","title":"柴犬当主播？这个新闻节目我看一天也不腻~","review":0,"author":"观察者网","mid":10330740,"created":1520829544,"length":"01:09","video_review":153,"aid":20679760,"bvid":"BV1YW411s7Gi","hide_click":false,"is_pay":0,"is_union_video":0},{"comment":403,"typeid":21,"play":18766,"pic":"//i2.hdslb.com/bfs/archive/2a310732a73f302f728b698f53dd036381ca68e4.jpg","subtitle":"","description":"3月11日晚7点左右，纽约东河一架欧直AS350观光直升机径直坠入河中，至少已有两人遇难","copyright":"","title":"纽约一观光直升机一头栽入河中，至少已有两人遇难...","review":0,"author":"观察者网","mid":10330740,"created":1520821994,"length":"00:32","video_review":38,"aid":20677085,"bvid":"BV1eW411s7ur","hide_click":false,"is_pay":0,"is_union_video":0},{"comment":297,"typeid":96,"play":24224,"pic":"//i0.hdslb.com/bfs/archive/5779e3a2dc745f16c6ac92d8fb2f1f3ac8cfbe65.jpg","subtitle":"","description":"https://youtu.be/qBzp36j0OXo\n【俄罗斯再秀一轮战略武器】据俄罗斯卫星网报道，俄军11日成功完成了一次“匕首”高超音速导弹实弹发射演习。由于米格-31飞机和超音速弹道导弹的低雷达能见度以及高机动性的性能特点，当今世界还没有能比拟“匕首”导弹系统的同类系统。","copyright":"","title":"俄罗斯再秀一轮战略武器：高超音速导弹实弹发射演习成功","review":0,"author":"观察者网","mid":10330740,"created":1520821633,"length":"01:37","video_review":114,"aid":20676552,"bvid":"BV1HW411s743","hide_click":false,"is_pay":0,"is_union_video":0},{"comment":749,"typeid":21,"play":123327,"pic":"//i0.hdslb.com/bfs/archive/07a79b87f707ff672996de9df36405713802a752.jpg","subtitle":"","description":"对没错，俄罗斯干涉美国大选的“新证据”就是这个没人听说过的页游……CNN表示，俄罗斯人想让该游戏在大选前爆红，虽然未能如愿，但这更证明了俄罗斯是多么处心积虑地试图干涉美国内政！新闻一播，网民们纷纷……求页游地址。","copyright":"","title":"别笑，这个页游真的是CNN找到的“新证据”","review":0,"author":"观察者网","mid":10330740,"created":1520764829,"length":"02:38","video_review":557,"aid":20648884,"bvid":"BV1sW411s7Uf","hide_click":false,"is_pay":0,"is_union_video":0},{"comment":1112,"typeid":96,"play":88875,"pic":"//i1.hdslb.com/bfs/archive/733792b17c312ee29e419649c32bc2cf705fd77c.jpg","subtitle":"","description":"特朗普同意与金正恩会面，这让白宫又震惊又紧张。3月10日，特朗普在宾州集会上提到对朝政策，表示“我可能离开，也可能坐下来谈出个对全世界来说最伟大的交易”。他还说，自己相信朝鲜的讲和意愿。","copyright":"","title":"特朗普：与朝会谈可能“最伟大”，日本都乐坏了","review":0,"author":"观察者网","mid":10330740,"created":1520740279,"length":"01:47","video_review":603,"aid":20634745,"bvid":"BV1uW411s7NG","hide_click":false,"is_pay":0,"is_union_video":0},{"comment":826,"typeid":174,"play":407492,"pic":"//i2.hdslb.com/bfs/archive/413547f4a41f7f4051fb1f9eca2a1e4a83b94c03.jpg","subtitle":"","description":"2月20日，上海城市交响乐团受邀在意大利演出结束后，准备回国时遇到飞机延误。94岁的指挥家曹鹏和30多位演奏者突发奇想，在罗马机场上演了一段即兴“快闪”，奏起了《我的祖国》，让不少在场的中国人热泪盈眶！","copyright":"","title":"罗马机场上演的这段即兴“快闪”，让不少中国人激动不已！","review":0,"author":"观察者网","mid":10330740,"created":1520654218,"length":"02:17","video_review":755,"aid":20585253,"bvid":"BV1PW411s72G","hide_click":false,"is_pay":0,"is_union_video":0},{"comment":348,"typeid":21,"play":104066,"pic":"//i0.hdslb.com/bfs/archive/fb2bef18c920f2baa3e554bca7751ff9584e9478.jpg","subtitle":"","description":"当中国环球电视网的埃塞俄比亚籍记者再次提起“茅坑国家”问题时，蒂勒森却玩起外交腔","copyright":"","title":"面对央视记者提问，蒂勒森的回答让美国媒体失望","review":0,"author":"观察者网","mid":10330740,"created":1520586089,"length":"00:49","video_review":82,"aid":20552472,"bvid":"BV1RW411W7cV","hide_click":false,"is_pay":0,"is_union_video":0},{"comment":152,"typeid":124,"play":492918,"pic":"//i0.hdslb.com/bfs/archive/e918e79ee9fe8b046d277128815031542aa4c178.jpg","subtitle":"","description":"中国的改革开放在动荡和混乱中起步，在国民经济一片萧条中起步，经过艰难的探索，中国的政治制度逐步定型，并成功地将中国引向了工业化、现代化。改革开放40年来，中国的政治体制有何变化？为什么东欧、苏联的改革纷纷失败，而中国的改革却获得了历史性的成功？是什么样的内在逻辑和正确经验促进和保障了中国的成功？\n2018年3月10日下午14:30，来观察者网直播间与房宁老师一起探讨答案吧！","copyright":"","title":"“（中国）要摆脱被别人欺负的局面”，得令！【观天下讲坛第16期预告】","review":0,"author":"观察者网","mid":10330740,"created":1520585592,"length":"04:05","video_review":51,"aid":20551486,"bvid":"BV1RW411W7Jt","hide_click":false,"is_pay":0,"is_union_video":0},{"comment":2129,"typeid":21,"play":423256,"pic":"//i1.hdslb.com/bfs/archive/b027f69cf58476d91319c5e07774e25070519846.jpg","subtitle":"","description":"台湾“独派社团”开记者会声援慈湖泼漆学生，蔡丁贵遭统派男子闯入狂喷生发剂","copyright":"","title":"台湾统派男子向“台独”秃头领袖喷生发剂","review":0,"author":"观察者网","mid":10330740,"created":1520585429,"length":"00:37","video_review":852,"aid":20552853,"bvid":"BV19W411W74E","hide_click":false,"is_pay":0,"is_union_video":0},{"comment":981,"typeid":21,"play":411493,"pic":"//i2.hdslb.com/bfs/archive/f3a25d0254d65da0566137fa95ca3c22e1b03e44.jpg","subtitle":"","description":"正在访问埃塞俄比亚的蒂勒森，于8日在非洲联盟(African Union)总部发表讲话，警告非洲国家“接受中国资金将有丧失主权的风险”。这番话迅速被非盟委员会主席当场怼回：“我们有自己的意愿。”","copyright":"","title":"中国援建的非盟总部，蒂勒森说中国坏话被非盟主席回怼","review":0,"author":"观察者网","mid":10330740,"created":1520585245,"length":"00:58","video_review":254,"aid":20549607,"bvid":"BV1XW411W74q","hide_click":false,"is_pay":0,"is_union_video":0},{"comment":1407,"typeid":124,"play":469557,"pic":"//i1.hdslb.com/bfs/archive/f5aeb5b3383adfe54ba0a25e83ada8117b696364.jpg","subtitle":"","description":"https://youtu.be/iwB0fAMH6Es\n【普京：我喜欢特朗普，但是美国的制度完全不靠谱】在纪录片《2018世界秩序》中，俄罗斯总统普京谈到和特朗普的关系时表示：“让我失望的并不是这个人，而是整个机制。”他直言：美国的政治体制效率低，不可预测。","copyright":"","title":"普京：我喜欢特朗普，但是美国的制度真不靠谱！","review":0,"author":"观察者网","mid":10330740,"created":1520582426,"length":"01:18","video_review":434,"aid":20550437,"bvid":"BV1RW411W7BY","hide_click":false,"is_pay":0,"is_union_video":0},{"comment":2170,"typeid":124,"play":1605785,"pic":"//i1.hdslb.com/bfs/archive/a9a7342f2f5f446fb013d07824996ecb5eb280de.jpg","subtitle":"","description":"在纪录片《2018世界秩序》中，对于部分西方媒体玩得手段，普京表示早就习以为常了，根本不会影响到情绪，想知道“当坏蛋什么感觉”，直接问那些坏蛋啊","copyright":"","title":"被问“当世界头号坏蛋什么感觉”，普京这么回答…","review":0,"author":"观察者网","mid":10330740,"created":1520579244,"length":"01:01","video_review":842,"aid":20548867,"bvid":"BV1XW411W7nb","hide_click":false,"is_pay":0,"is_union_video":0},{"comment":156,"typeid":75,"play":32129,"pic":"//i2.hdslb.com/bfs/archive/f9500472b02e16578650d6bf0bde8c359e53e92a.jpg","subtitle":"","description":"难得的闲暇时光被主人伺候着梳头，看看狗子幸福的笑容！不仅要梳头，全身都要梳一梳。","copyright":"","title":"认证!这是一只爱梳头的狗子！","review":0,"author":"观察者网","mid":10330740,"created":1520576513,"length":"00:33","video_review":72,"aid":20547670,"bvid":"BV1XW411W7Yx","hide_click":false,"is_pay":0,"is_union_video":0},{"comment":739,"typeid":96,"play":25877,"pic":"//i1.hdslb.com/bfs/archive/7f3b16da13695429b84d9c1136e1a1f62e19fb8c.jpg","subtitle":"","description":"【金正恩：我想尽快见到特朗普】美国当地时间8日晚，郑义溶在白宫前门外召开记者会时表示：特朗普已经同意朝鲜最高领导人的会面邀请，预计将在5月前举行。金正恩表示愿意推动无核化进程，在会面期间不会进行核试验与导弹试验。","copyright":"","title":"特朗普5月前将会见金正恩","review":0,"author":"观察者网","mid":10330740,"created":1520564767,"length":"00:57","video_review":37,"aid":20540012,"bvid":"BV16W411W7a2","hide_click":false,"is_pay":0,"is_union_video":0}]},"page":{"count":6208,"pn":146,"ps":30}}}