{"code":0,"message":"0","ttl":1,"data":{"list":{"tlist":{"160":{"tid":160,"count":167,"name":"生活"},"177":{"tid":177,"count":1,"name":"纪录片"},"181":{"tid":181,"count":1,"name":"影视"},"3":{"tid":3,"count":1,"name":"音乐"},"36":{"tid":36,"count":884,"name":"科技"},"5":{"tid":5,"count":3,"name":"娱乐"}},"vlist":[{"comment":857,"typeid":96,"play":235878,"pic":"//i2.hdslb.com/bfs/archive/971ee4cad1c4180a766971be89c780a1ef890c0c.jpg","subtitle":"","description":"一勺思想1月份月底捞","copyright":"","title":"【月底捞】道理我都懂，我就想问翟币债券什么时候发售？","review":0,"author":"观视频工作室","mid":54992199,"created":1580555815,"length":"06:13","video_review":1803,"aid":86129704,"bvid":"BV1t7411x7ra","hide_click":false,"is_pay":0,"is_union_video":0},{"comment":780,"typeid":96,"play":203889,"pic":"//i0.hdslb.com/bfs/archive/3e1731fc5244df537343cf38be9b4db0f9ffc66e.jpg","subtitle":"","description":"袁老师解读：肺炎疫情成国际突发公共卫生事件，对中国影响多大？","copyright":"","title":"【代发】袁老师：肺炎疫情成国际突发公共卫生事件，对中国影响多大？","review":0,"author":"观视频工作室","mid":54992199,"created":1580541374,"length":"07:37","video_review":1399,"aid":86085251,"bvid":"BV157411x7WQ","hide_click":false,"is_pay":0,"is_union_video":0},{"comment":3217,"typeid":96,"play":1498880,"pic":"//i0.hdslb.com/bfs/archive/c81e0cfcd847b068612733a18a03ce272537c54c.jpg","subtitle":"","description":"观视频2019答案年终秀\n金灿荣问答","copyright":"","title":"【答案7.5】金灿荣问答：对台湾，该摊牌了","review":0,"author":"观视频工作室","mid":54992199,"created":1580481548,"length":"31:58","video_review":31396,"aid":85944287,"bvid":"BV1U7411B73E","hide_click":false,"is_pay":0,"is_union_video":0},{"comment":5535,"typeid":96,"play":992943,"pic":"//i1.hdslb.com/bfs/archive/8925402ef63c94787fd34365cc89427dd6127169.jpg","subtitle":"","description":"睡前消息0131\n抗击病毒不能反应过度；\n中国家用电器发展；\n耐克新跑鞋强化长跑运动员。","copyright":"","title":"【睡前消息71】为什么说为了防疫反应过度，也会“杀死”国人？","review":0,"author":"观视频工作室","mid":54992199,"created":1580479431,"length":"20:49","video_review":15065,"aid":85978030,"bvid":"BV1Z7411B7ze","hide_click":false,"is_pay":0,"is_union_video":0},{"comment":178,"typeid":96,"play":754798,"pic":"//i2.hdslb.com/bfs/archive/5f58f1d796d8c3b7f121c63145c22f251ac47d2e.jpg","subtitle":"","description":"眉山论剑：警惕有人趁中国抗击疫情做空中国经济","copyright":"","title":"【眉山论剑】抗击病毒同时，警惕有人想趁机做空中国经济！","review":0,"author":"观视频工作室","mid":54992199,"created":1580381142,"length":"04:49","video_review":0,"aid":85731200,"bvid":"BV1X7411q7B8","hide_click":false,"is_pay":0,"is_union_video":0},{"comment":1537,"typeid":96,"play":360038,"pic":"//i2.hdslb.com/bfs/archive/95a3bdf87b7d6c2a30a72d32e5489a558c78ecb0.jpg","subtitle":"","description":"一勺思想·范从来：中国会爆发金融危机吗？","copyright":"","title":"【一勺思想】有人说中国爆发金融危机概率高达66%，怎么算的？","review":0,"author":"观视频工作室","mid":54992199,"created":1580300719,"length":"08:59","video_review":1903,"aid":85614671,"bvid":"BV1U7411z71F","hide_click":false,"is_pay":0,"is_union_video":0},{"comment":1289,"typeid":124,"play":460909,"pic":"//i2.hdslb.com/bfs/archive/1c4c92a10b0ff960f8747dbee3a89e396c1101b2.jpg","subtitle":"","description":"睡前消息特别版：收音机和电视机","copyright":"","title":"【睡前故事】当年的收音机和电视机，对一个中国家庭多重要？","review":0,"author":"观视频工作室","mid":54992199,"created":1580216772,"length":"05:25","video_review":2303,"aid":85457959,"bvid":"BV167411r75P","hide_click":false,"is_pay":0,"is_union_video":0},{"comment":1721,"typeid":96,"play":411263,"pic":"//i2.hdslb.com/bfs/archive/5f58f1d796d8c3b7f121c63145c22f251ac47d2e.jpg","subtitle":"","description":"眉山论剑：走出去探索化解“三座大山”新路","copyright":"","title":"【眉山论剑】教育医疗养老，是否已经成为中国新的“三座大山”？","review":0,"author":"观视频工作室","mid":54992199,"created":1580210319,"length":"11:04","video_review":3098,"aid":85434652,"bvid":"BV1y7411r7QW","hide_click":false,"is_pay":0,"is_union_video":0},{"comment":189,"typeid":21,"play":119577,"pic":"//i1.hdslb.com/bfs/archive/5ed26e6423d3e4c99ad93e893b54eb2aa81c4ab5.png","subtitle":"","description":"奋战在全世界的中国外交工作人员，向大家拜年啦！","copyright":"","title":"全世界的中国外交人员，怎么过春节？","review":0,"author":"观视频工作室","mid":54992199,"created":1580186972,"length":"06:45","video_review":210,"aid":85377729,"bvid":"BV177411r7Kg","hide_click":false,"is_pay":0,"is_union_video":0},{"comment":13,"typeid":96,"play":215100,"pic":"//i1.hdslb.com/bfs/archive/3d5c260a10e6b17631886fe5d71b701a1bc4914c.jpg","subtitle":"","description":"观视频2019答案年终秀\n胡锡进问答","copyright":"","title":"【答案6.5】胡锡进问答：我发表的言论，需要经过领导同意吗？","review":0,"author":"观视频工作室","mid":54992199,"created":1580131745,"length":"41:07","video_review":0,"aid":85306238,"bvid":"BV1P7411r7xt","hide_click":false,"is_pay":0,"is_union_video":0},{"comment":4159,"typeid":96,"play":594582,"pic":"//i1.hdslb.com/bfs/archive/7a25279845503283845a8dddd13133a16595d988.jpg","subtitle":"","description":"一勺思想·范从来：中国金融是否反噬经济","copyright":"","title":"【一勺思想】为什么中国现在实体经济衰落，反而要开放金融？","review":0,"author":"观视频工作室","mid":54992199,"created":1580118688,"length":"07:30","video_review":4979,"aid":85271594,"bvid":"BV19741167mV","hide_click":false,"is_pay":0,"is_union_video":0},{"comment":3050,"typeid":124,"play":605372,"pic":"//i1.hdslb.com/bfs/archive/793df671104e93aaf9d7babc514f27075963fdb6.jpg","subtitle":"","description":"睡前消息特别版——睡前故事：国民变迁史\n今天讲讲吃的故事，在解放战争当中，“小米加步枪”里面的“小米”到底有多神奇？","copyright":"","title":"【睡前故事】“小米加步枪”里的小米，如何帮助共产党解放中国？","review":0,"author":"观视频工作室","mid":54992199,"created":1580040903,"length":"06:54","video_review":5990,"aid":85052390,"bvid":"BV177411k7c6","hide_click":false,"is_pay":0,"is_union_video":0},{"comment":617,"typeid":124,"play":146327,"pic":"//i1.hdslb.com/bfs/archive/0014879e65cb723b81e043652d2af0129ed69827.jpg","subtitle":"","description":"从书说起·余亮：读莫里斯《西方将主宰多久》（中）","copyright":"","title":"【从书说起】西方将主宰多久（中）——宋朝当年差点发生工业革命？","review":0,"author":"观视频工作室","mid":54992199,"created":1580035935,"length":"13:42","video_review":804,"aid":85123624,"bvid":"BV167411k7hX","hide_click":false,"is_pay":0,"is_union_video":0},{"comment":725,"typeid":96,"play":262162,"pic":"//i1.hdslb.com/bfs/archive/5bfad0e9252c77702c15560b4d969c7ebe35b66a.jpg","subtitle":"","description":"非同凡想0125：苏莱曼尼之死","copyright":"","title":"【非同凡想】特朗普：当年我早说过美国总统会为了选举打伊朗","review":0,"author":"观视频工作室","mid":54992199,"created":1579955778,"length":"11:13","video_review":981,"aid":85008455,"bvid":"BV1L7411k7FM","hide_click":false,"is_pay":0,"is_union_video":0},{"comment":1440,"typeid":96,"play":436510,"pic":"//i2.hdslb.com/bfs/archive/b7fd8eca98a9a6b79d81886185ea8775b8c5e247.jpg","subtitle":"","description":"一勺思想·马丁雅克：西方衰落与中国崛起","copyright":"","title":"【一勺思想】马丁雅克：10年前中国人不爱提统治世界，但今天他们开始思考了","review":0,"author":"观视频工作室","mid":54992199,"created":1579947287,"length":"04:35","video_review":1385,"aid":84989670,"bvid":"BV1Z7411r7fi","hide_click":false,"is_pay":0,"is_union_video":0},{"comment":429,"typeid":21,"play":128279,"pic":"//i1.hdslb.com/bfs/archive/269e7cabf443712099be98d0ec6423682ccc235e.jpg","subtitle":"","description":"-","copyright":"","title":"张维为老师在达沃斯给大家拜年啦！","review":0,"author":"观视频工作室","mid":54992199,"created":1579873626,"length":"00:51","video_review":474,"aid":84886410,"bvid":"BV1W7411Y7pu","hide_click":false,"is_pay":0,"is_union_video":0},{"comment":4974,"typeid":96,"play":814417,"pic":"//i0.hdslb.com/bfs/archive/4366e060a9ed25792f042bfe2071210a9e4869b3.jpg","subtitle":"","description":"睡前消息第70期\n除夕夜，督工给B站同学们“表白”啦","copyright":"","title":"【睡前消息70】除夕夜，督工还有几件事想和大家聊聊！","review":0,"author":"观视频工作室","mid":54992199,"created":1579860901,"length":"22:03","video_review":12899,"aid":84827103,"bvid":"BV1P7411Y7bG","hide_click":false,"is_pay":0,"is_union_video":0},{"comment":1195,"typeid":96,"play":192416,"pic":"//i2.hdslb.com/bfs/archive/86d2c15662b382b1f7c84eecba0bf28fc1607c2e.jpg","subtitle":"","description":"陈平老师新春拜年视频","copyright":"","title":"陈平老师来给大家拜年啦！","review":0,"author":"观视频工作室","mid":54992199,"created":1579830710,"length":"02:59","video_review":2994,"aid":84797170,"bvid":"BV1d7411a73y","hide_click":false,"is_pay":0,"is_union_video":0},{"comment":844,"typeid":96,"play":380371,"pic":"//i1.hdslb.com/bfs/archive/7e1ad4a1e2c66d5e5797eb44212240421fbd9fc8.jpg","subtitle":"","description":"一勺思想·马丁雅克：脱欧困境背后的日落帝国","copyright":"","title":"【一勺思想】英国人脱欧困境的背后，是一场不愿醒来的帝国梦","review":0,"author":"观视频工作室","mid":54992199,"created":1579779972,"length":"05:20","video_review":788,"aid":84730826,"bvid":"BV1i7411a7Nt","hide_click":false,"is_pay":0,"is_union_video":0},{"comment":1840,"typeid":96,"play":307468,"pic":"//i0.hdslb.com/bfs/archive/4274809b391308d6bb55a50fe78ce7a963f72948.jpg","subtitle":"","description":"观视频2019答案年终秀\n马前卒现场观众问答部分","copyright":"","title":"【答案5.5】马前卒问答：思考医疗问题，首先要把医生“当人看”","review":0,"author":"观视频工作室","mid":54992199,"created":1579700956,"length":"17:26","video_review":2790,"aid":84603030,"bvid":"BV1q7411e7ft","hide_click":false,"is_pay":0,"is_union_video":0},{"comment":2434,"typeid":21,"play":279905,"pic":"//i1.hdslb.com/bfs/archive/b74ed02b6731a11a3ec5d2ff412fa748b79fb365.png","subtitle":"","description":"也说：老马怎么过春节？","copyright":"","title":"【也说】今年上春晚的明星，80后还认得出几个？","review":0,"author":"观视频工作室","mid":54992199,"created":1579686387,"length":"09:18","video_review":4956,"aid":84567439,"bvid":"BV1x7411e7m1","hide_click":false,"is_pay":0,"is_union_video":0},{"comment":6221,"typeid":124,"play":1081394,"pic":"//i0.hdslb.com/bfs/archive/acf3ba4808a9f56ed77fe107a9d5fa20d877f10d.png","subtitle":"","description":"睡前消息0121\r\n中央介入恒丰银行重组；\r\n魔兽世界15周年；\r\n国民党为何还有那么多支持者。","copyright":"","title":"【睡前消息69】真正奇怪的是，竟然还有500多万台湾人选国民党？","review":0,"author":"观视频工作室","mid":54992199,"created":1579611372,"length":"22:33","video_review":16726,"aid":84418713,"bvid":"BV1D7411Y7dE","hide_click":false,"is_pay":0,"is_union_video":0},{"comment":2437,"typeid":96,"play":752244,"pic":"//i1.hdslb.com/bfs/archive/f0f86bdb0507b2cebb6ae5e7cb6768141fb1069a.png","subtitle":"","description":"眉山论剑0121\r\n警惕美国内斗引发世界乱局","copyright":"","title":"【眉山论剑】为什么刺杀伊朗高官，说明美国已经变得非常危险","review":0,"author":"观视频工作室","mid":54992199,"created":1579597900,"length":"07:11","video_review":3433,"aid":84416157,"bvid":"BV1S7411Y7Yd","hide_click":false,"is_pay":0,"is_union_video":0},{"comment":747,"typeid":96,"play":345880,"pic":"//i2.hdslb.com/bfs/archive/e6da14a8a864f47c1913ca5c9e3bd2429d21c2d6.png","subtitle":"","description":"一勺思想·马丁雅克：全球分离主义运动","copyright":"","title":"【一勺思想】马丁雅克：澳门人尝过苦日子，但香港人还没有","review":0,"author":"观视频工作室","mid":54992199,"created":1579523620,"length":"05:37","video_review":822,"aid":84299156,"bvid":"BV1C7411v76D","hide_click":false,"is_pay":0,"is_union_video":0},{"comment":28,"typeid":124,"play":253632,"pic":"//i2.hdslb.com/bfs/archive/2d7d4711d4a872e052377be5617c67affb6cf9b8.png","subtitle":"","description":"从书说起·余亮：读《何长工回忆录》","copyright":"","title":"【从书说起】读《何长工回忆录》——共产党人是为谁打天下？","review":0,"author":"观视频工作室","mid":54992199,"created":1579447729,"length":"19:06","video_review":0,"aid":84173931,"bvid":"BV1K7411v7km","hide_click":false,"is_pay":0,"is_union_video":0},{"comment":26154,"typeid":96,"play":1196497,"pic":"//i1.hdslb.com/bfs/archive/0be6d337ff23201a14cc492f01263ac76c2ce72d.png","subtitle":"","description":"睡前消息0119\r\n同盾公司被查事件；\r\n中国在迪拜建光热电站工程；\r\n吃二甲双胍可以减肥；\r\n女子开车进故宫事件。","copyright":"","title":"【睡前消息68】对开车进故宫这事，我们要批评到点子上！","review":0,"author":"观视频工作室","mid":54992199,"created":1579440587,"length":"18:53","video_review":20727,"aid":84156987,"bvid":"BV1G7411v7Av","hide_click":false,"is_pay":0,"is_union_video":0},{"comment":1028,"typeid":96,"play":792625,"pic":"//i1.hdslb.com/bfs/archive/ff5167a8f628440bb3cb945b2dfc41ee2d8a6e84.jpg","subtitle":"","description":"非同凡想0118：蔡英文","copyright":"","title":"【非同凡想】蔡英文再次当选，会让“武统”越来越近吗？","review":0,"author":"观视频工作室","mid":54992199,"created":1579353931,"length":"10:14","video_review":10767,"aid":83960968,"bvid":"BV1Q7411i7ZJ","hide_click":false,"is_pay":0,"is_union_video":0},{"comment":1032,"typeid":96,"play":178836,"pic":"//i0.hdslb.com/bfs/archive/0f388c2ce6de6b29d976e1b3ca193688252bbe79.png","subtitle":"","description":"观视频2019答案年终秀\r\n丁一凡老师观众问答部分","copyright":"","title":"【答案4.5】丁一凡问答：中国政治体制的关键，在于能够回应民众诉求","review":0,"author":"观视频工作室","mid":54992199,"created":1579351639,"length":"09:26","video_review":2269,"aid":83999356,"bvid":"BV1A7411q7ma","hide_click":false,"is_pay":0,"is_union_video":0},{"comment":855,"typeid":96,"play":281678,"pic":"//i0.hdslb.com/bfs/archive/85602871ba7fc5596b4e7a9eaa50097e25aac1db.jpg","subtitle":"","description":"张维为《这就是中国》第45期精彩片段3","copyright":"","title":"【这就是中国】毛克疾：种姓制度，当年却推动了印度历史的发展？","review":0,"author":"观视频工作室","mid":54992199,"created":1579327642,"length":"03:45","video_review":877,"aid":83947507,"bvid":"BV1i7411i7ZP","hide_click":false,"is_pay":0,"is_union_video":0},{"comment":2456,"typeid":124,"play":681570,"pic":"//i1.hdslb.com/bfs/archive/ee9585a80fdcdda1c395ca044ee9f5e5f68c67f4.jpg","subtitle":"","description":"睡前消息0117\n被三大运营商集体拉黑的河南村庄；\n去年社保基金收益率15.5%；\n贵州近30万贫困人群完成搬迁。","copyright":"","title":"【睡前消息67】河南有个村，被三大运营商集体“拉黑”了……","review":0,"author":"观视频工作室","mid":54992199,"created":1579266357,"length":"16:43","video_review":10224,"aid":83860075,"bvid":"BV11J411E7og","hide_click":false,"is_pay":0,"is_union_video":0}]},"page":{"count":1057,"pn":8,"ps":30}}}